{"kind":"qpxExpress#tripsSearch","trips":{"data":{"aircraft":[{"code":"319","kind":"qpxexpress#aircraftData","name":"Airbus A319"},{"code":"320","kind":"qpxexpress#aircraftData","name":"Airbus A320"},{"code":"321","kind":"qpxexpress#aircraftData","name":"Airbus A321"},{"code":"735","kind":"qpxexpress#aircraftData","name":"Boeing 737"},{"code":"AR1","kind":"qpxexpress#aircraftData","name":"Avro RJ100"},{"code":"CR9","kind":"qpxexpress#aircraftData","name":"Canadair RJ 900"},{"code":"DH4","kind":"qpxexpress#aircraftData","name":"De Havilland-Bombardier Dash-8"}],"airport":[{"city":"ATH","code":"ATH","kind":"qpxexpress#airportData","name":"Athens Eleftherios Venizelos"},{"city":"BCN","code":"BCN","kind":"qpxexpress#airportData","name":"Barcelona"},{"city":"BRU","code":"BRU","kind":"qpxexpress#airportData","name":"Brussels Airport"},{"city":"CPH","code":"CPH","kind":"qpxexpress#airportData","name":"Copenhagen Kastrup"},{"city":"FRA","code":"FRA","kind":"qpxexpress#airportData","name":"Frankfurt International"},{"city":"HAM","code":"HAM","kind":"qpxexpress#airportData","name":"Hamburg Airport"},{"city":"MUC","code":"MUC","kind":"qpxexpress#airportData","name":"Munich Franz Joseph Strauss Int'l"},{"city":"RIX","code":"RIX","kind":"qpxexpress#airportData","name":"Riga International"},{"city":"STR","code":"STR","kind":"qpxexpress#airportData","name":"Stuttgart"}],"carrier":[{"code":"4U","kind":"qpxexpress#carrierData","name":"Germanwings GmbH"},{"code":"A3","kind":"qpxexpress#carrierData","name":"Aegean Airlines S.A."},{"code":"BT","kind":"qpxexpress#carrierData","name":"Air Baltic Corporation AS"},{"code":"IB","kind":"qpxexpress#carrierData","name":"Iberia Lineas Aereas de Espana S.A."},{"code":"SK","kind":"qpxexpress#carrierData","name":"Scandinavian Airlines System (SAS)"},{"code":"SN","kind":"qpxexpress#carrierData","name":"SN Brussels Airlines"}],"city":[{"code":"ATH","kind":"qpxexpress#cityData","name":"Athens"},{"code":"BCN","kind":"qpxexpress#cityData","name":"Barcelona"},{"code":"BRU","kind":"qpxexpress#cityData","name":"Brussels"},{"code":"CPH","kind":"qpxexpress#cityData","name":"Copenhagen"},{"code":"FRA","kind":"qpxexpress#cityData","name":"Frankfurt"},{"code":"HAM","kind":"qpxexpress#cityData","name":"Hamburg"},{"code":"MUC","kind":"qpxexpress#cityData","name":"Munich"},{"code":"RIX","kind":"qpxexpress#cityData","name":"Riga"},{"code":"STR","kind":"qpxexpress#cityData","name":"Stuttgart"}],"kind":"qpxexpress#data","tax":[{"id":"RA_002","kind":"qpxexpress#taxData","name":"German Passenger Service Charge"},{"id":"YQ_F","kind":"qpxexpress#taxData","name":"A3 YQ surcharge"},{"id":"ZO_003","kind":"qpxexpress#taxData","name":"Danish Passenger Service Charge"},{"id":"RD_002","kind":"qpxexpress#taxData","name":"German Passenger Service Charge"},{"id":"LV_001","kind":"qpxexpress#taxData","name":"Latvia LV"},{"id":"OG_001","kind":"qpxexpress#taxData","name":"Spain OG"},{"id":"OY_001","kind":"qpxexpress#taxData","name":"German Air Transport Tax"},{"id":"OH_001","kind":"qpxexpress#taxData","name":"Latvia OH"},{"id":"YR_I","kind":"qpxexpress#taxData","name":"IB YR surcharge"},{"id":"YR_F","kind":"qpxexpress#taxData","name":"A3 YR surcharge"},{"id":"JD_001","kind":"qpxexpress#taxData","name":"Spain JD"},{"id":"YQ_I","kind":"qpxexpress#taxData","name":"SN YQ surcharge"},{"id":"QV_001","kind":"qpxexpress#taxData","name":"Spain QV"},{"id":"DE_001","kind":"qpxexpress#taxData","name":"German Airport Security Tax"},{"id":"BE_001","kind":"qpxexpress#taxData","name":"Belgium BE"}]},"kind":"qpxexpress#tripOptions","requestId":"8lsvkehn9oRSidxcL0MBKQ","tripOption":[{"id":"Rns2hzSE8zQMCRWPJ1iNLU001","kind":"qpxexpress#tripOption","pricing":[{"baseFareTotal":"EUR120.00","fare":[{"basisCode":"S2A3","carrier":"A3","destination":"ATH","id":"AQTkJZ6bbr9fDbNOOrvWjDeH/lZqL7A/R4qmYyR/L","kind":"qpxexpress#fareInfo","origin":"HAM"}],"fareCalculation":"HAM A3 ATH Q41.60 M 89.77S2A3 NUC 131.37 END ROE 0.913391 FARE EUR 120.00 XT 4.05DE 7.50OY 9.93RA 3.00YQ","kind":"qpxexpress#pricingInfo","latestTicketingTime":"2015-05-29T05:24-04:00","passengers":{"adultCount":1,"kind":"qpxexpress#passengerCounts"},"ptc":"ADT","refundable":true,"saleFareTotal":"EUR120.00","saleTaxTotal":"EUR24.48","saleTotal":"EUR144.48","segmentPricing":[{"fareId":"AQTkJZ6bbr9fDbNOOrvWjDeH/lZqL7A/R4qmYyR/L","freeBaggageOption":[{"bagDescriptor":[{"commercialName":"UPTO50LB 23KG BAGGAGE","count":1,"description":["Up to 50 lb/23 kg"],"kind":"qpxexpress#bagDescriptor","subcode":"0C3"},{"commercialName":"GOLF EQUIP UP TO 15KG 140CM","count":1,"description":["Small","Up to 33 lb/15 kg"],"kind":"qpxexpress#bagDescriptor","subcode":"S28"},{"commercialName":"GOLF EQUIP UP TO 32KG  2M","count":1,"description":["Medium","Up to 70 lb/32 kg"],"kind":"qpxexpress#bagDescriptor","subcode":"S29"},{"commercialName":"GOLF EQUIP UP TO 32KG OVER 2M","count":1,"description":["Large","Up to 70 lb/32 kg"],"kind":"qpxexpress#bagDescriptor","subcode":"S30"},{"commercialName":"SKI EQUIP UP TO 15KG 140CM","count":1,"description":["Small","Up to 33 lb/15 kg"],"kind":"qpxexpress#bagDescriptor","subcode":"S31"},{"commercialName":"SKI EQUIP UP TO 32KG 2M","count":1,"description":["Medium","Up to 70 lb/32 kg"],"kind":"qpxexpress#bagDescriptor","subcode":"S32"},{"commercialName":"SKI EQUIP UP TO 32KG OVER 2M","count":1,"description":["Large","Up to 70 lb/32 kg"],"kind":"qpxexpress#bagDescriptor","subcode":"S33"},{"commercialName":"WATER SKI EQUIP UPTO15KG 140CM","count":1,"description":["Small","Up to 33 lb/15 kg"],"kind":"qpxexpress#bagDescriptor","subcode":"S07"},{"commercialName":"WATER SKI EQUIP UP TO 32KG 2M","count":1,"description":["Medium","Up to 70 lb/32 kg"],"kind":"qpxexpress#bagDescriptor","subcode":"S08"},{"commercialName":"WATER SKI EQ UPTO 32KG OVER 2M","count":1,"description":["Large","Up to 70 lb/32 kg"],"kind":"qpxexpress#bagDescriptor","subcode":"S09"},{"commercialName":"SNOWBOARD UP TO 15KG 140CM","count":1,"description":["Small","Up to 33 lb/15 kg"],"kind":"qpxexpress#bagDescriptor","subcode":"S34"},{"commercialName":"SNOWBOARD UP TO 32KG  2M","count":1,"description":["Medium","Up to 70 lb/32 kg"],"kind":"qpxexpress#bagDescriptor","subcode":"S35"},{"commercialName":"SNOWBOARD UP TO 32KG OVER 2M","count":1,"description":["Large","Up to 70 lb/32 kg"],"kind":"qpxexpress#bagDescriptor","subcode":"S36"}],"kind":"qpxexpress#freeBaggageAllowance","pieces":1}],"kind":"qpxexpress#segmentPricing","segmentId":"GpxMKAOBESruoB9w"}],"tax":[{"chargeType":"CARRIER_SURCHARGE","code":"YQ","id":"YQ_F","kind":"qpxexpress#taxInfo","salePrice":"EUR3.00"},{"chargeType":"GOVERNMENT","code":"DE","country":"DE","id":"DE_001","kind":"qpxexpress#taxInfo","salePrice":"EUR4.05"},{"chargeType":"GOVERNMENT","code":"RA","country":"DE","id":"RA_002","kind":"qpxexpress#taxInfo","salePrice":"EUR9.93"},{"chargeType":"GOVERNMENT","code":"OY","country":"DE","id":"OY_001","kind":"qpxexpress#taxInfo","salePrice":"EUR7.50"}]}],"saleTotal":"EUR144.48","slice":[{"duration":190,"kind":"qpxexpress#sliceInfo","segment":[{"bookingCode":"S","bookingCodeCount":9,"cabin":"COACH","duration":190,"flight":{"carrier":"A3","number":"849"},"id":"GpxMKAOBESruoB9w","kind":"qpxexpress#segmentInfo","leg":[{"aircraft":"320","arrivalTime":"2015-05-29T15:35+03:00","departureTime":"2015-05-29T11:25+02:00","destination":"ATH","duration":190,"id":"LDz+1xXJQmF0NbIF","kind":"qpxexpress#legInfo","meal":"Hot Meal","mileage":1270,"origin":"HAM","originTerminal":"2"}],"marriedSegmentGroup":"0"}]}]},{"id":"Rns2hzSE8zQMCRWPJ1iNLU00C","kind":"qpxexpress#tripOption","pricing":[{"baseFareTotal":"EUR208.00","fare":[{"basisCode":"WNCWGDE","carrier":"4U","destination":"ATH","id":"AHMSm29rklE6BufRqWsOU8G1eZavc4ZyYvFn7DPtxOnM","kind":"qpxexpress#fareInfo","origin":"HAM"}],"fareCalculation":"HAM 4U X/STR 4U ATH 227.72WNCWGDE NUC 227.72 END ROE 0.913391 FARE EUR 208.00 XT 9.10DE 15.00OY 7.61RA 15.16RD","kind":"qpxexpress#pricingInfo","latestTicketingTime":"2015-05-25T15:46-04:00","passengers":{"adultCount":1,"kind":"qpxexpress#passengerCounts"},"ptc":"ADT","saleFareTotal":"EUR208.00","saleTaxTotal":"EUR46.87","saleTotal":"EUR254.87","segmentPricing":[{"fareId":"AHMSm29rklE6BufRqWsOU8G1eZavc4ZyYvFn7DPtxOnM","freeBaggageOption":[{"bagDescriptor":[{"commercialName":"UPTO50LB 23KG AND62LI 158LCM","count":1,"description":["Up to 50 lb/23 kg","Up to 62 li/158 lcm"],"kind":"qpxexpress#bagDescriptor","subcode":"0GO"},{"commercialName":"ASSISTIVE DEVICES","kind":"qpxexpress#bagDescriptor","subcode":"0GM"}],"kind":"qpxexpress#freeBaggageAllowance","pieces":1}],"kind":"qpxexpress#segmentPricing","segmentId":"GzSFdRMWlchZrQNw"},{"fareId":"AHMSm29rklE6BufRqWsOU8G1eZavc4ZyYvFn7DPtxOnM","freeBaggageOption":[{"bagDescriptor":[{"commercialName":"UPTO50LB 23KG AND62LI 158LCM","count":1,"description":["Up to 50 lb/23 kg","Up to 62 li/158 lcm"],"kind":"qpxexpress#bagDescriptor","subcode":"0GO"},{"commercialName":"ASSISTIVE DEVICES","kind":"qpxexpress#bagDescriptor","subcode":"0GM"}],"kind":"qpxexpress#freeBaggageAllowance","pieces":1}],"kind":"qpxexpress#segmentPricing","segmentId":"Gy9-f9iDLcdpJ5+v"}],"tax":[{"chargeType":"GOVERNMENT","code":"OY","country":"DE","id":"OY_001","kind":"qpxexpress#taxInfo","salePrice":"EUR15.00"},{"chargeType":"GOVERNMENT","code":"RD","country":"DE","id":"RD_002","kind":"qpxexpress#taxInfo","salePrice":"EUR15.16"},{"chargeType":"GOVERNMENT","code":"DE","country":"DE","id":"DE_001","kind":"qpxexpress#taxInfo","salePrice":"EUR9.10"},{"chargeType":"GOVERNMENT","code":"RA","country":"DE","id":"RA_002","kind":"qpxexpress#taxInfo","salePrice":"EUR7.61"}]}],"saleTotal":"EUR254.87","slice":[{"duration":1065,"kind":"qpxexpress#sliceInfo","segment":[{"bookingCode":"W","bookingCodeCount":9,"cabin":"COACH","connectionDuration":835,"duration":75,"flight":{"carrier":"4U","number":"2043"},"id":"Gy9-f9iDLcdpJ5+v","kind":"qpxexpress#segmentInfo","leg":[{"aircraft":"319","arrivalTime":"2015-05-29T21:50+02:00","departureTime":"2015-05-29T20:35+02:00","destination":"STR","destinationTerminal":"1","duration":75,"id":"LYjXVF6oeo3LlgKP","kind":"qpxexpress#legInfo","meal":"Refreshments","mileage":342,"origin":"HAM","originTerminal":"2"}],"marriedSegmentGroup":"0"},{"bookingCode":"W","bookingCodeCount":9,"cabin":"COACH","duration":155,"flight":{"carrier":"4U","number":"2684"},"id":"GzSFdRMWlchZrQNw","kind":"qpxexpress#segmentInfo","leg":[{"aircraft":"320","arrivalTime":"2015-05-30T15:20+03:00","departureTime":"2015-05-30T11:45+02:00","destination":"ATH","duration":155,"id":"Laj46pDe-fneoBMW","kind":"qpxexpress#legInfo","meal":"Refreshments","mileage":1044,"origin":"STR","originTerminal":"1"}],"marriedSegmentGroup":"1"}]}]},{"id":"Rns2hzSE8zQMCRWPJ1iNLU008","kind":"qpxexpress#tripOption","pricing":[{"baseFareTotal":"EUR191.00","fare":[{"basisCode":"W2A3DE","carrier":"A3","destination":"ATH","id":"AIelGDeTK0d5kaWL0F5SJOHwFcHLQu6I1Njq3hNcFdGLa","kind":"qpxexpress#fareInfo","origin":"HAM"}],"fareCalculation":"HAM A3 X/FRA A3 ATH Q41.60 M 167.50W2A3DE NUC 209.10 END ROE 0.913391 FARE EUR 191.00 XT 4.05DE 7.50OY 21.19RA 9.93RD 6.00YQ 38.00YR","kind":"qpxexpress#pricingInfo","latestTicketingTime":"2015-05-29T02:59-04:00","passengers":{"adultCount":1,"kind":"qpxexpress#passengerCounts"},"ptc":"ADT","refundable":true,"saleFareTotal":"EUR191.00","saleTaxTotal":"EUR86.67","saleTotal":"EUR277.67","segmentPricing":[{"fareId":"AIelGDeTK0d5kaWL0F5SJOHwFcHLQu6I1Njq3hNcFdGLa","freeBaggageOption":[{"bagDescriptor":[{"commercialName":"UPTO50LB 23KG BAGGAGE","count":1,"description":["Up to 50 lb/23 kg"],"kind":"qpxexpress#bagDescriptor","subcode":"0C3"},{"commercialName":"GOLF EQUIP UP TO 15KG 140CM","count":1,"description":["Small","Up to 33 lb/15 kg"],"kind":"qpxexpress#bagDescriptor","subcode":"S28"},{"commercialName":"GOLF EQUIP UP TO 32KG  2M","count":1,"description":["Medium","Up to 70 lb/32 kg"],"kind":"qpxexpress#bagDescriptor","subcode":"S29"},{"commercialName":"GOLF EQUIP UP TO 32KG OVER 2M","count":1,"description":["Large","Up to 70 lb/32 kg"],"kind":"qpxexpress#bagDescriptor","subcode":"S30"},{"commercialName":"SKI EQUIP UP TO 15KG 140CM","count":1,"description":["Small","Up to 33 lb/15 kg"],"kind":"qpxexpress#bagDescriptor","subcode":"S31"},{"commercialName":"SKI EQUIP UP TO 32KG 2M","count":1,"description":["Medium","Up to 70 lb/32 kg"],"kind":"qpxexpress#bagDescriptor","subcode":"S32"},{"commercialName":"SKI EQUIP UP TO 32KG OVER 2M","count":1,"description":["Large","Up to 70 lb/32 kg"],"kind":"qpxexpress#bagDescriptor","subcode":"S33"},{"commercialName":"WATER SKI EQUIP UPTO15KG 140CM","count":1,"description":["Small","Up to 33 lb/15 kg"],"kind":"qpxexpress#bagDescriptor","subcode":"S07"},{"commercialName":"WATER SKI EQUIP UP TO 32KG 2M","count":1,"description":["Medium","Up to 70 lb/32 kg"],"kind":"qpxexpress#bagDescriptor","subcode":"S08"},{"commercialName":"WATER SKI EQ UPTO 32KG OVER 2M","count":1,"description":["Large","Up to 70 lb/32 kg"],"kind":"qpxexpress#bagDescriptor","subcode":"S09"},{"commercialName":"SNOWBOARD UP TO 15KG 140CM","count":1,"description":["Small","Up to 33 lb/15 kg"],"kind":"qpxexpress#bagDescriptor","subcode":"S34"},{"commercialName":"SNOWBOARD UP TO 32KG  2M","count":1,"description":["Medium","Up to 70 lb/32 kg"],"kind":"qpxexpress#bagDescriptor","subcode":"S35"},{"commercialName":"SNOWBOARD UP TO 32KG OVER 2M","count":1,"description":["Large","Up to 70 lb/32 kg"],"kind":"qpxexpress#bagDescriptor","subcode":"S36"}],"kind":"qpxexpress#freeBaggageAllowance","pieces":1}],"kind":"qpxexpress#segmentPricing","segmentId":"Ga0ZijYPiRFe9t3A"},{"fareId":"AIelGDeTK0d5kaWL0F5SJOHwFcHLQu6I1Njq3hNcFdGLa","freeBaggageOption":[{"bagDescriptor":[{"commercialName":"UPTO50LB 23KG BAGGAGE","count":1,"description":["Up to 50 lb/23 kg"],"kind":"qpxexpress#bagDescriptor","subcode":"0C3"},{"commercialName":"GOLF EQUIP UP TO 15KG 140CM","count":1,"description":["Small","Up to 33 lb/15 kg"],"kind":"qpxexpress#bagDescriptor","subcode":"S28"},{"commercialName":"GOLF EQUIP UP TO 32KG  2M","count":1,"description":["Medium","Up to 70 lb/32 kg"],"kind":"qpxexpress#bagDescriptor","subcode":"S29"},{"commercialName":"GOLF EQUIP UP TO 32KG OVER 2M","count":1,"description":["Large","Up to 70 lb/32 kg"],"kind":"qpxexpress#bagDescriptor","subcode":"S30"},{"commercialName":"SKI EQUIP UP TO 15KG 140CM","count":1,"description":["Small","Up to 33 lb/15 kg"],"kind":"qpxexpress#bagDescriptor","subcode":"S31"},{"commercialName":"SKI EQUIP UP TO 32KG 2M","count":1,"description":["Medium","Up to 70 lb/32 kg"],"kind":"qpxexpress#bagDescriptor","subcode":"S32"},{"commercialName":"SKI EQUIP UP TO 32KG OVER 2M","count":1,"description":["Large","Up to 70 lb/32 kg"],"kind":"qpxexpress#bagDescriptor","subcode":"S33"},{"commercialName":"WATER SKI EQUIP UPTO15KG 140CM","count":1,"description":["Small","Up to 33 lb/15 kg"],"kind":"qpxexpress#bagDescriptor","subcode":"S07"},{"commercialName":"WATER SKI EQUIP UP TO 32KG 2M","count":1,"description":["Medium","Up to 70 lb/32 kg"],"kind":"qpxexpress#bagDescriptor","subcode":"S08"},{"commercialName":"WATER SKI EQ UPTO 32KG OVER 2M","count":1,"description":["Large","Up to 70 lb/32 kg"],"kind":"qpxexpress#bagDescriptor","subcode":"S09"},{"commercialName":"SNOWBOARD UP TO 15KG 140CM","count":1,"description":["Small","Up to 33 lb/15 kg"],"kind":"qpxexpress#bagDescriptor","subcode":"S34"},{"commercialName":"SNOWBOARD UP TO 32KG  2M","count":1,"description":["Medium","Up to 70 lb/32 kg"],"kind":"qpxexpress#bagDescriptor","subcode":"S35"},{"commercialName":"SNOWBOARD UP TO 32KG OVER 2M","count":1,"description":["Large","Up to 70 lb/32 kg"],"kind":"qpxexpress#bagDescriptor","subcode":"S36"}],"kind":"qpxexpress#freeBaggageAllowance","pieces":1}],"kind":"qpxexpress#segmentPricing","segmentId":"GvouwLABkUrYis8G"}],"tax":[{"chargeType":"GOVERNMENT","code":"RA","country":"DE","id":"RA_002","kind":"qpxexpress#taxInfo","salePrice":"EUR21.19"},{"chargeType":"CARRIER_SURCHARGE","code":"YQ","id":"YQ_F","kind":"qpxexpress#taxInfo","salePrice":"EUR6.00"},{"chargeType":"GOVERNMENT","code":"DE","country":"DE","id":"DE_001","kind":"qpxexpress#taxInfo","salePrice":"EUR4.05"},{"chargeType":"GOVERNMENT","code":"RD","country":"DE","id":"RD_002","kind":"qpxexpress#taxInfo","salePrice":"EUR9.93"},{"chargeType":"GOVERNMENT","code":"OY","country":"DE","id":"OY_001","kind":"qpxexpress#taxInfo","salePrice":"EUR7.50"},{"chargeType":"CARRIER_SURCHARGE","code":"YR","id":"YR_F","kind":"qpxexpress#taxInfo","salePrice":"EUR38.00"}]}],"saleTotal":"EUR277.67","slice":[{"duration":715,"kind":"qpxexpress#sliceInfo","segment":[{"bookingCode":"W","bookingCodeCount":4,"cabin":"COACH","connectionDuration":465,"duration":75,"flight":{"carrier":"A3","number":"1567"},"id":"Ga0ZijYPiRFe9t3A","kind":"qpxexpress#segmentInfo","leg":[{"aircraft":"319","arrivalTime":"2015-05-29T10:15+02:00","departureTime":"2015-05-29T09:00+02:00","destination":"FRA","destinationTerminal":"1","duration":75,"id":"Lz1-w5EH6cR28a8-","kind":"qpxexpress#legInfo","meal":"Meal","mileage":255,"operatingDisclosure":"OPERATED BY LUFTHANSA","origin":"HAM","originTerminal":"2"}],"marriedSegmentGroup":"0"},{"bookingCode":"W","bookingCodeCount":9,"cabin":"COACH","duration":175,"flight":{"carrier":"A3","number":"833"},"id":"GvouwLABkUrYis8G","kind":"qpxexpress#segmentInfo","leg":[{"aircraft":"321","arrivalTime":"2015-05-29T21:55+03:00","departureTime":"2015-05-29T18:00+02:00","destination":"ATH","duration":175,"id":"LeCl+nIvki8Bb1H-","kind":"qpxexpress#legInfo","meal":"Hot Meal","mileage":1127,"origin":"FRA","originTerminal":"1"}],"marriedSegmentGroup":"1"}]}]},{"id":"Rns2hzSE8zQMCRWPJ1iNLU00E","kind":"qpxexpress#tripOption","pricing":[{"baseFareTotal":"EUR205.00","fare":[{"basisCode":"QDETH9PL","carrier":"BT","destination":"ATH","id":"AsNtKpZ/nEalp1H8qBtvOENmANRO3YxeuZTCtezLWKtw","kind":"qpxexpress#fareInfo","origin":"HAM"}],"fareCalculation":"HAM BT X/RIX BT ATH 224.43QDETH9PL NUC 224.43 END ROE 0.913391 FARE EUR 205.00 XT 4.05DE 7.50OY 9.93RA 0.28LV 1.00OH 54.00YQ","kind":"qpxexpress#pricingInfo","latestTicketingTime":"2015-05-26T15:46-04:00","passengers":{"adultCount":1,"kind":"qpxexpress#passengerCounts"},"ptc":"ADT","refundable":true,"saleFareTotal":"EUR205.00","saleTaxTotal":"EUR76.76","saleTotal":"EUR281.76","segmentPricing":[{"fareId":"AsNtKpZ/nEalp1H8qBtvOENmANRO3YxeuZTCtezLWKtw","freeBaggageOption":[{"bagDescriptor":[{"count":1,"kind":"qpxexpress#bagDescriptor","subcode":"0C2"},{"kind":"qpxexpress#bagDescriptor","subcode":"0DC"},{"kind":"qpxexpress#bagDescriptor","subcode":"0DD"},{"kind":"qpxexpress#bagDescriptor","subcode":"0EE"},{"kind":"qpxexpress#bagDescriptor","subcode":"0EC"},{"kind":"qpxexpress#bagDescriptor","subcode":"0ED"},{"kind":"qpxexpress#bagDescriptor","subcode":"0D6"},{"kind":"qpxexpress#bagDescriptor","subcode":"0BS"}],"kind":"qpxexpress#freeBaggageAllowance","pieces":1}],"kind":"qpxexpress#segmentPricing","segmentId":"Gicz1AmO2idI7rJp"},{"fareId":"AsNtKpZ/nEalp1H8qBtvOENmANRO3YxeuZTCtezLWKtw","freeBaggageOption":[{"bagDescriptor":[{"count":1,"kind":"qpxexpress#bagDescriptor","subcode":"0C2"},{"kind":"qpxexpress#bagDescriptor","subcode":"0DC"},{"kind":"qpxexpress#bagDescriptor","subcode":"0DD"},{"kind":"qpxexpress#bagDescriptor","subcode":"0EE"},{"kind":"qpxexpress#bagDescriptor","subcode":"0EC"},{"kind":"qpxexpress#bagDescriptor","subcode":"0ED"},{"kind":"qpxexpress#bagDescriptor","subcode":"0D6"},{"kind":"qpxexpress#bagDescriptor","subcode":"0BS"}],"kind":"qpxexpress#freeBaggageAllowance","pieces":1}],"kind":"qpxexpress#segmentPricing","segmentId":"GpCADaRUpuK9Y+3l"}],"tax":[{"chargeType":"CARRIER_SURCHARGE","code":"YQ","id":"YQ_F","kind":"qpxexpress#taxInfo","salePrice":"EUR54.00"},{"chargeType":"GOVERNMENT","code":"LV","country":"LV","id":"LV_001","kind":"qpxexpress#taxInfo","salePrice":"EUR0.28"},{"chargeType":"GOVERNMENT","code":"OH","country":"LV","id":"OH_001","kind":"qpxexpress#taxInfo","salePrice":"EUR1.00"},{"chargeType":"GOVERNMENT","code":"DE","country":"DE","id":"DE_001","kind":"qpxexpress#taxInfo","salePrice":"EUR4.05"},{"chargeType":"GOVERNMENT","code":"RA","country":"DE","id":"RA_002","kind":"qpxexpress#taxInfo","salePrice":"EUR9.93"},{"chargeType":"GOVERNMENT","code":"OY","country":"DE","id":"OY_001","kind":"qpxexpress#taxInfo","salePrice":"EUR7.50"}]}],"saleTotal":"EUR281.76","slice":[{"duration":1330,"kind":"qpxexpress#sliceInfo","segment":[{"bookingCode":"Q","bookingCodeCount":4,"cabin":"COACH","connectionDuration":1015,"duration":115,"flight":{"carrier":"BT","number":"254"},"id":"Gicz1AmO2idI7rJp","kind":"qpxexpress#segmentInfo","leg":[{"aircraft":"DH4","arrivalTime":"2015-05-29T22:35+03:00","departureTime":"2015-05-29T19:40+02:00","destination":"RIX","duration":115,"id":"LhuPKPPdingM+eBV","kind":"qpxexpress#legInfo","meal":"Food and Beverages for Purchase","mileage":593,"origin":"HAM","originTerminal":"1"}],"marriedSegmentGroup":"0"},{"bookingCode":"Q","bookingCodeCount":9,"cabin":"COACH","duration":200,"flight":{"carrier":"BT","number":"611"},"id":"GpCADaRUpuK9Y+3l","kind":"qpxexpress#segmentInfo","leg":[{"aircraft":"735","arrivalTime":"2015-05-30T18:50+03:00","departureTime":"2015-05-30T15:30+03:00","destination":"ATH","duration":200,"id":"LW3XaoYKtj4sdJXg","kind":"qpxexpress#legInfo","meal":"Food and Beverages for Purchase","mileage":1311,"origin":"RIX"}],"marriedSegmentGroup":"1"}]}]},{"id":"Rns2hzSE8zQMCRWPJ1iNLU00F","kind":"qpxexpress#tripOption","pricing":[{"baseFareTotal":"EUR222.00","fare":[{"basisCode":"LWYNVY","carrier":"IB","destination":"ATH","id":"AhR8IQyShz95Ba2ZfyJ+Y2aJNQ5GK6UbODboucWOufk6TW2ZebcooonVG4NVn2uGVy5QlAQBxRkgx7T9zrRHEhCtRDkE0LE","kind":"qpxexpress#fareInfo","origin":"HAM"}],"fareCalculation":"HAM IB X/BCN IB ATH 243.05LWYNVY NUC 243.05 END ROE 0.913391 FARE EUR 222.00 XT 4.05DE 7.50OY 9.93RA 15.32JD 0.58OG 3.78QV 37.00YQ 1.00YR","kind":"qpxexpress#pricingInfo","latestTicketingTime":"2015-05-25T15:46-04:00","passengers":{"adultCount":1,"kind":"qpxexpress#passengerCounts"},"ptc":"ADT","saleFareTotal":"EUR222.00","saleTaxTotal":"EUR79.16","saleTotal":"EUR301.16","segmentPricing":[{"fareId":"AhR8IQyShz95Ba2ZfyJ+Y2aJNQ5GK6UbODboucWOufk6TW2ZebcooonVG4NVn2uGVy5QlAQBxRkgx7T9zrRHEhCtRDkE0LE","freeBaggageOption":[{"bagDescriptor":[{"commercialName":"UP TO 23 KG AND 158 LCM","count":1,"description":["Up to 50 lb/23 kg","Up to 62 li/158 lcm"],"kind":"qpxexpress#bagDescriptor","subcode":"0GO"},{"commercialName":"GOLF EQUIPMENT UP TO 15 KG","count":1,"description":["Golf Equipment","Up to 33 lb/15 kg"],"kind":"qpxexpress#bagDescriptor","subcode":"0D4"},{"commercialName":"SKI SNOW","count":1,"description":["Ski Equipment"],"kind":"qpxexpress#bagDescriptor","subcode":"0DD"},{"commercialName":"FISHING EQUIPMENT","count":1,"description":["Fishing Equipment"],"kind":"qpxexpress#bagDescriptor","subcode":"0D6"},{"commercialName":"STROLLER OR PUSHCHAIR","description":["Stroller/Pushchair"],"kind":"qpxexpress#bagDescriptor","subcode":"0F4"}],"kind":"qpxexpress#freeBaggageAllowance","pieces":1}],"kind":"qpxexpress#segmentPricing","segmentId":"GJwPCbd6h+NdYT+i"},{"fareId":"AhR8IQyShz95Ba2ZfyJ+Y2aJNQ5GK6UbODboucWOufk6TW2ZebcooonVG4NVn2uGVy5QlAQBxRkgx7T9zrRHEhCtRDkE0LE","freeBaggageOption":[{"bagDescriptor":[{"commercialName":"UP TO 23 KG AND 158 LCM","count":1,"description":["Up to 50 lb/23 kg","Up to 62 li/158 lcm"],"kind":"qpxexpress#bagDescriptor","subcode":"0GO"},{"commercialName":"GOLF EQUIPMENT UP TO 15 KG","count":1,"description":["Golf Equipment","Up to 33 lb/15 kg"],"kind":"qpxexpress#bagDescriptor","subcode":"0D4"},{"commercialName":"SKI SNOW","count":1,"description":["Ski Equipment"],"kind":"qpxexpress#bagDescriptor","subcode":"0DD"},{"commercialName":"FISHING EQUIPMENT","count":1,"description":["Fishing Equipment"],"kind":"qpxexpress#bagDescriptor","subcode":"0D6"},{"commercialName":"STROLLER OR PUSHCHAIR","description":["Stroller/Pushchair"],"kind":"qpxexpress#bagDescriptor","subcode":"0F4"}],"kind":"qpxexpress#freeBaggageAllowance","pieces":1}],"kind":"qpxexpress#segmentPricing","segmentId":"G+C4E4xax2KbVt-w"}],"tax":[{"chargeType":"CARRIER_SURCHARGE","code":"YQ","id":"YQ_F","kind":"qpxexpress#taxInfo","salePrice":"EUR37.00"},{"chargeType":"GOVERNMENT","code":"JD","country":"ES","id":"JD_001","kind":"qpxexpress#taxInfo","salePrice":"EUR15.32"},{"chargeType":"GOVERNMENT","code":"QV","country":"ES","id":"QV_001","kind":"qpxexpress#taxInfo","salePrice":"EUR3.78"},{"chargeType":"GOVERNMENT","code":"OG","country":"ES","id":"OG_001","kind":"qpxexpress#taxInfo","salePrice":"EUR0.58"},{"chargeType":"CARRIER_SURCHARGE","code":"YR","id":"YR_I","kind":"qpxexpress#taxInfo","salePrice":"EUR1.00"},{"chargeType":"GOVERNMENT","code":"DE","country":"DE","id":"DE_001","kind":"qpxexpress#taxInfo","salePrice":"EUR4.05"},{"chargeType":"GOVERNMENT","code":"RA","country":"DE","id":"RA_002","kind":"qpxexpress#taxInfo","salePrice":"EUR9.93"},{"chargeType":"GOVERNMENT","code":"OY","country":"DE","id":"OY_001","kind":"qpxexpress#taxInfo","salePrice":"EUR7.50"}]}],"saleTotal":"EUR301.16","slice":[{"duration":1280,"kind":"qpxexpress#sliceInfo","segment":[{"bookingCode":"L","bookingCodeCount":4,"cabin":"COACH","connectionDuration":960,"duration":150,"flight":{"carrier":"IB","number":"5445"},"id":"G+C4E4xax2KbVt-w","kind":"qpxexpress#segmentInfo","leg":[{"aircraft":"320","arrivalTime":"2015-05-29T17:55+02:00","departureTime":"2015-05-29T15:25+02:00","destination":"BCN","destinationTerminal":"1","duration":150,"id":"LQr7JD2d2QtysLxD","kind":"qpxexpress#legInfo","meal":"Food and Beverages for Purchase","mileage":927,"operatingDisclosure":"OPERATED BY VUELING AIRLINES","origin":"HAM","originTerminal":"1"}],"marriedSegmentGroup":"0"},{"bookingCode":"L","bookingCodeCount":4,"cabin":"COACH","duration":170,"flight":{"carrier":"IB","number":"5766"},"id":"GJwPCbd6h+NdYT+i","kind":"qpxexpress#segmentInfo","leg":[{"aircraft":"320","arrivalTime":"2015-05-30T13:45+03:00","departureTime":"2015-05-30T09:55+02:00","destination":"ATH","duration":170,"id":"LVdRyhvUDMI9D6Ka","kind":"qpxexpress#legInfo","meal":"Food and Beverages for Purchase","mileage":1182,"operatingDisclosure":"OPERATED BY VUELING AIRLINES","origin":"BCN","originTerminal":"1"}],"marriedSegmentGroup":"1"}]}]},{"id":"Rns2hzSE8zQMCRWPJ1iNLU00D","kind":"qpxexpress#tripOption","pricing":[{"baseFareTotal":"EUR258.00","fare":[{"basisCode":"QNCWGDE","carrier":"4U","destination":"ATH","id":"AneP4G3VSgiJwO6TOeec7gHgwGZ/1YuTg39YD1aBvU62","kind":"qpxexpress#fareInfo","origin":"HAM"}],"fareCalculation":"HAM 4U X/STR 4U ATH 282.46QNCWGDE NUC 282.46 END ROE 0.913391 FARE EUR 258.00 XT 9.10DE 15.00OY 7.61RA 15.16RD","kind":"qpxexpress#pricingInfo","latestTicketingTime":"2015-05-25T15:46-04:00","passengers":{"adultCount":1,"kind":"qpxexpress#passengerCounts"},"ptc":"ADT","saleFareTotal":"EUR258.00","saleTaxTotal":"EUR46.87","saleTotal":"EUR304.87","segmentPricing":[{"fareId":"AneP4G3VSgiJwO6TOeec7gHgwGZ/1YuTg39YD1aBvU62","freeBaggageOption":[{"bagDescriptor":[{"commercialName":"UPTO50LB 23KG AND62LI 158LCM","count":1,"description":["Up to 50 lb/23 kg","Up to 62 li/158 lcm"],"kind":"qpxexpress#bagDescriptor","subcode":"0GO"},{"commercialName":"ASSISTIVE DEVICES","kind":"qpxexpress#bagDescriptor","subcode":"0GM"}],"kind":"qpxexpress#freeBaggageAllowance","pieces":1}],"kind":"qpxexpress#segmentPricing","segmentId":"GzSFdRMWlchZrQNw"},{"fareId":"AneP4G3VSgiJwO6TOeec7gHgwGZ/1YuTg39YD1aBvU62","freeBaggageOption":[{"bagDescriptor":[{"commercialName":"UPTO50LB 23KG AND62LI 158LCM","count":1,"description":["Up to 50 lb/23 kg","Up to 62 li/158 lcm"],"kind":"qpxexpress#bagDescriptor","subcode":"0GO"},{"commercialName":"ASSISTIVE DEVICES","kind":"qpxexpress#bagDescriptor","subcode":"0GM"}],"kind":"qpxexpress#freeBaggageAllowance","pieces":1}],"kind":"qpxexpress#segmentPricing","segmentId":"GIsYwewgxPAYnURj"}],"tax":[{"chargeType":"GOVERNMENT","code":"OY","country":"DE","id":"OY_001","kind":"qpxexpress#taxInfo","salePrice":"EUR15.00"},{"chargeType":"GOVERNMENT","code":"RD","country":"DE","id":"RD_002","kind":"qpxexpress#taxInfo","salePrice":"EUR15.16"},{"chargeType":"GOVERNMENT","code":"DE","country":"DE","id":"DE_001","kind":"qpxexpress#taxInfo","salePrice":"EUR9.10"},{"chargeType":"GOVERNMENT","code":"RA","country":"DE","id":"RA_002","kind":"qpxexpress#taxInfo","salePrice":"EUR7.61"}]}],"saleTotal":"EUR304.87","slice":[{"duration":1150,"kind":"qpxexpress#sliceInfo","segment":[{"bookingCode":"Q","bookingCodeCount":9,"cabin":"COACH","connectionDuration":920,"duration":75,"flight":{"carrier":"4U","number":"7048"},"id":"GIsYwewgxPAYnURj","kind":"qpxexpress#segmentInfo","leg":[{"aircraft":"319","arrivalTime":"2015-05-29T20:25+02:00","departureTime":"2015-05-29T19:10+02:00","destination":"STR","destinationTerminal":"1","duration":75,"id":"LMAawsmYAMLl4n-J","kind":"qpxexpress#legInfo","meal":"Refreshments","mileage":342,"origin":"HAM","originTerminal":"2"}],"marriedSegmentGroup":"0"},{"bookingCode":"Q","bookingCodeCount":9,"cabin":"COACH","duration":155,"flight":{"carrier":"4U","number":"2684"},"id":"GzSFdRMWlchZrQNw","kind":"qpxexpress#segmentInfo","leg":[{"aircraft":"320","arrivalTime":"2015-05-30T15:20+03:00","departureTime":"2015-05-30T11:45+02:00","destination":"ATH","duration":155,"id":"Laj46pDe-fneoBMW","kind":"qpxexpress#legInfo","meal":"Refreshments","mileage":1044,"origin":"STR","originTerminal":"1"}],"marriedSegmentGroup":"1"}]}]},{"id":"Rns2hzSE8zQMCRWPJ1iNLU007","kind":"qpxexpress#tripOption","pricing":[{"baseFareTotal":"EUR205.00","fare":[{"basisCode":"Q2A3DE","carrier":"A3","destination":"ATH","id":"ATSC/CKZ4neLQNIlNvyPR69lqOXl5wIFWMg4RGcyFF9v3","kind":"qpxexpress#fareInfo","origin":"HAM"}],"fareCalculation":"HAM A3 X/MUC A3 ATH M 224.43Q2A3DE NUC 224.43 END ROE 0.913391 FARE EUR 205.00 XT 4.05DE 7.50OY 16.66RA 9.93RD 6.00YQ 76.00YR","kind":"qpxexpress#pricingInfo","latestTicketingTime":"2015-05-29T01:59-04:00","passengers":{"adultCount":1,"kind":"qpxexpress#passengerCounts"},"ptc":"ADT","refundable":true,"saleFareTotal":"EUR205.00","saleTaxTotal":"EUR120.14","saleTotal":"EUR325.14","segmentPricing":[{"fareId":"ATSC/CKZ4neLQNIlNvyPR69lqOXl5wIFWMg4RGcyFF9v3","freeBaggageOption":[{"bagDescriptor":[{"commercialName":"UPTO50LB 23KG BAGGAGE","count":1,"description":["Up to 50 lb/23 kg"],"kind":"qpxexpress#bagDescriptor","subcode":"0C3"},{"commercialName":"GOLF EQUIP UP TO 15KG 140CM","count":1,"description":["Small","Up to 33 lb/15 kg"],"kind":"qpxexpress#bagDescriptor","subcode":"S28"},{"commercialName":"GOLF EQUIP UP TO 32KG  2M","count":1,"description":["Medium","Up to 70 lb/32 kg"],"kind":"qpxexpress#bagDescriptor","subcode":"S29"},{"commercialName":"GOLF EQUIP UP TO 32KG OVER 2M","count":1,"description":["Large","Up to 70 lb/32 kg"],"kind":"qpxexpress#bagDescriptor","subcode":"S30"},{"commercialName":"SKI EQUIP UP TO 15KG 140CM","count":1,"description":["Small","Up to 33 lb/15 kg"],"kind":"qpxexpress#bagDescriptor","subcode":"S31"},{"commercialName":"SKI EQUIP UP TO 32KG 2M","count":1,"description":["Medium","Up to 70 lb/32 kg"],"kind":"qpxexpress#bagDescriptor","subcode":"S32"},{"commercialName":"SKI EQUIP UP TO 32KG OVER 2M","count":1,"description":["Large","Up to 70 lb/32 kg"],"kind":"qpxexpress#bagDescriptor","subcode":"S33"},{"commercialName":"WATER SKI EQUIP UPTO15KG 140CM","count":1,"description":["Small","Up to 33 lb/15 kg"],"kind":"qpxexpress#bagDescriptor","subcode":"S07"},{"commercialName":"WATER SKI EQUIP UP TO 32KG 2M","count":1,"description":["Medium","Up to 70 lb/32 kg"],"kind":"qpxexpress#bagDescriptor","subcode":"S08"},{"commercialName":"WATER SKI EQ UPTO 32KG OVER 2M","count":1,"description":["Large","Up to 70 lb/32 kg"],"kind":"qpxexpress#bagDescriptor","subcode":"S09"},{"commercialName":"SNOWBOARD UP TO 15KG 140CM","count":1,"description":["Small","Up to 33 lb/15 kg"],"kind":"qpxexpress#bagDescriptor","subcode":"S34"},{"commercialName":"SNOWBOARD UP TO 32KG  2M","count":1,"description":["Medium","Up to 70 lb/32 kg"],"kind":"qpxexpress#bagDescriptor","subcode":"S35"},{"commercialName":"SNOWBOARD UP TO 32KG OVER 2M","count":1,"description":["Large","Up to 70 lb/32 kg"],"kind":"qpxexpress#bagDescriptor","subcode":"S36"}],"kind":"qpxexpress#freeBaggageAllowance","pieces":1}],"kind":"qpxexpress#segmentPricing","segmentId":"GhRXPXTXYxFm4t8d"},{"fareId":"ATSC/CKZ4neLQNIlNvyPR69lqOXl5wIFWMg4RGcyFF9v3","freeBaggageOption":[{"bagDescriptor":[{"commercialName":"UPTO50LB 23KG BAGGAGE","count":1,"description":["Up to 50 lb/23 kg"],"kind":"qpxexpress#bagDescriptor","subcode":"0C3"},{"commercialName":"GOLF EQUIP UP TO 15KG 140CM","count":1,"description":["Small","Up to 33 lb/15 kg"],"kind":"qpxexpress#bagDescriptor","subcode":"S28"},{"commercialName":"GOLF EQUIP UP TO 32KG  2M","count":1,"description":["Medium","Up to 70 lb/32 kg"],"kind":"qpxexpress#bagDescriptor","subcode":"S29"},{"commercialName":"GOLF EQUIP UP TO 32KG OVER 2M","count":1,"description":["Large","Up to 70 lb/32 kg"],"kind":"qpxexpress#bagDescriptor","subcode":"S30"},{"commercialName":"SKI EQUIP UP TO 15KG 140CM","count":1,"description":["Small","Up to 33 lb/15 kg"],"kind":"qpxexpress#bagDescriptor","subcode":"S31"},{"commercialName":"SKI EQUIP UP TO 32KG 2M","count":1,"description":["Medium","Up to 70 lb/32 kg"],"kind":"qpxexpress#bagDescriptor","subcode":"S32"},{"commercialName":"SKI EQUIP UP TO 32KG OVER 2M","count":1,"description":["Large","Up to 70 lb/32 kg"],"kind":"qpxexpress#bagDescriptor","subcode":"S33"},{"commercialName":"WATER SKI EQUIP UPTO15KG 140CM","count":1,"description":["Small","Up to 33 lb/15 kg"],"kind":"qpxexpress#bagDescriptor","subcode":"S07"},{"commercialName":"WATER SKI EQUIP UP TO 32KG 2M","count":1,"description":["Medium","Up to 70 lb/32 kg"],"kind":"qpxexpress#bagDescriptor","subcode":"S08"},{"commercialName":"WATER SKI EQ UPTO 32KG OVER 2M","count":1,"description":["Large","Up to 70 lb/32 kg"],"kind":"qpxexpress#bagDescriptor","subcode":"S09"},{"commercialName":"SNOWBOARD UP TO 15KG 140CM","count":1,"description":["Small","Up to 33 lb/15 kg"],"kind":"qpxexpress#bagDescriptor","subcode":"S34"},{"commercialName":"SNOWBOARD UP TO 32KG  2M","count":1,"description":["Medium","Up to 70 lb/32 kg"],"kind":"qpxexpress#bagDescriptor","subcode":"S35"},{"commercialName":"SNOWBOARD UP TO 32KG OVER 2M","count":1,"description":["Large","Up to 70 lb/32 kg"],"kind":"qpxexpress#bagDescriptor","subcode":"S36"}],"kind":"qpxexpress#freeBaggageAllowance","pieces":1}],"kind":"qpxexpress#segmentPricing","segmentId":"G2aVxbWydHzJAd2u"}],"tax":[{"chargeType":"CARRIER_SURCHARGE","code":"YQ","id":"YQ_F","kind":"qpxexpress#taxInfo","salePrice":"EUR6.00"},{"chargeType":"CARRIER_SURCHARGE","code":"YR","id":"YR_F","kind":"qpxexpress#taxInfo","salePrice":"EUR76.00"},{"chargeType":"GOVERNMENT","code":"RA","country":"DE","id":"RA_002","kind":"qpxexpress#taxInfo","salePrice":"EUR16.66"},{"chargeType":"GOVERNMENT","code":"DE","country":"DE","id":"DE_001","kind":"qpxexpress#taxInfo","salePrice":"EUR4.05"},{"chargeType":"GOVERNMENT","code":"RD","country":"DE","id":"RD_002","kind":"qpxexpress#taxInfo","salePrice":"EUR9.93"},{"chargeType":"GOVERNMENT","code":"OY","country":"DE","id":"OY_001","kind":"qpxexpress#taxInfo","salePrice":"EUR7.50"}]}],"saleTotal":"EUR325.14","slice":[{"duration":545,"kind":"qpxexpress#sliceInfo","segment":[{"bookingCode":"Q","bookingCodeCount":4,"cabin":"COACH","connectionDuration":330,"duration":75,"flight":{"carrier":"A3","number":"1575"},"id":"GhRXPXTXYxFm4t8d","kind":"qpxexpress#segmentInfo","leg":[{"aircraft":"321","arrivalTime":"2015-05-29T09:15+02:00","departureTime":"2015-05-29T08:00+02:00","destination":"MUC","destinationTerminal":"2","duration":75,"id":"LfVkqc5bO6rLMyVY","kind":"qpxexpress#legInfo","meal":"Meal","mileage":372,"operatingDisclosure":"OPERATED BY LUFTHANSA","origin":"HAM","originTerminal":"2"}],"marriedSegmentGroup":"0"},{"bookingCode":"Q","bookingCodeCount":4,"cabin":"COACH","duration":140,"flight":{"carrier":"A3","number":"1806"},"id":"G2aVxbWydHzJAd2u","kind":"qpxexpress#segmentInfo","leg":[{"aircraft":"321","arrivalTime":"2015-05-29T18:05+03:00","departureTime":"2015-05-29T14:45+02:00","destination":"ATH","duration":140,"id":"LIi8zTihDGegZHq1","kind":"qpxexpress#legInfo","meal":"Meal","mileage":942,"operatingDisclosure":"OPERATED BY LUFTHANSA","origin":"MUC","originTerminal":"2"}],"marriedSegmentGroup":"1"}]}]},{"id":"Rns2hzSE8zQMCRWPJ1iNLU005","kind":"qpxexpress#tripOption","pricing":[{"baseFareTotal":"EUR205.00","fare":[{"basisCode":"Q2A3DE","carrier":"A3","destination":"ATH","id":"ATSC/CKZ4neLQNIlNvyPR69lqOXl5wIFWMg4RGcyFF9v3","kind":"qpxexpress#fareInfo","origin":"HAM"}],"fareCalculation":"HAM A3 X/MUC A3 ATH M 224.43Q2A3DE NUC 224.43 END ROE 0.913391 FARE EUR 205.00 XT 4.05DE 7.50OY 16.66RA 9.93RD 6.00YQ 76.00YR","kind":"qpxexpress#pricingInfo","latestTicketingTime":"2015-05-29T02:59-04:00","passengers":{"adultCount":1,"kind":"qpxexpress#passengerCounts"},"ptc":"ADT","refundable":true,"saleFareTotal":"EUR205.00","saleTaxTotal":"EUR120.14","saleTotal":"EUR325.14","segmentPricing":[{"fareId":"ATSC/CKZ4neLQNIlNvyPR69lqOXl5wIFWMg4RGcyFF9v3","freeBaggageOption":[{"bagDescriptor":[{"commercialName":"UPTO50LB 23KG BAGGAGE","count":1,"description":["Up to 50 lb/23 kg"],"kind":"qpxexpress#bagDescriptor","subcode":"0C3"},{"commercialName":"GOLF EQUIP UP TO 15KG 140CM","count":1,"description":["Small","Up to 33 lb/15 kg"],"kind":"qpxexpress#bagDescriptor","subcode":"S28"},{"commercialName":"GOLF EQUIP UP TO 32KG  2M","count":1,"description":["Medium","Up to 70 lb/32 kg"],"kind":"qpxexpress#bagDescriptor","subcode":"S29"},{"commercialName":"GOLF EQUIP UP TO 32KG OVER 2M","count":1,"description":["Large","Up to 70 lb/32 kg"],"kind":"qpxexpress#bagDescriptor","subcode":"S30"},{"commercialName":"SKI EQUIP UP TO 15KG 140CM","count":1,"description":["Small","Up to 33 lb/15 kg"],"kind":"qpxexpress#bagDescriptor","subcode":"S31"},{"commercialName":"SKI EQUIP UP TO 32KG 2M","count":1,"description":["Medium","Up to 70 lb/32 kg"],"kind":"qpxexpress#bagDescriptor","subcode":"S32"},{"commercialName":"SKI EQUIP UP TO 32KG OVER 2M","count":1,"description":["Large","Up to 70 lb/32 kg"],"kind":"qpxexpress#bagDescriptor","subcode":"S33"},{"commercialName":"WATER SKI EQUIP UPTO15KG 140CM","count":1,"description":["Small","Up to 33 lb/15 kg"],"kind":"qpxexpress#bagDescriptor","subcode":"S07"},{"commercialName":"WATER SKI EQUIP UP TO 32KG 2M","count":1,"description":["Medium","Up to 70 lb/32 kg"],"kind":"qpxexpress#bagDescriptor","subcode":"S08"},{"commercialName":"WATER SKI EQ UPTO 32KG OVER 2M","count":1,"description":["Large","Up to 70 lb/32 kg"],"kind":"qpxexpress#bagDescriptor","subcode":"S09"},{"commercialName":"SNOWBOARD UP TO 15KG 140CM","count":1,"description":["Small","Up to 33 lb/15 kg"],"kind":"qpxexpress#bagDescriptor","subcode":"S34"},{"commercialName":"SNOWBOARD UP TO 32KG  2M","count":1,"description":["Medium","Up to 70 lb/32 kg"],"kind":"qpxexpress#bagDescriptor","subcode":"S35"},{"commercialName":"SNOWBOARD UP TO 32KG OVER 2M","count":1,"description":["Large","Up to 70 lb/32 kg"],"kind":"qpxexpress#bagDescriptor","subcode":"S36"}],"kind":"qpxexpress#freeBaggageAllowance","pieces":1}],"kind":"qpxexpress#segmentPricing","segmentId":"GDvhNwpi-8lR0Kg1"},{"fareId":"ATSC/CKZ4neLQNIlNvyPR69lqOXl5wIFWMg4RGcyFF9v3","freeBaggageOption":[{"bagDescriptor":[{"commercialName":"UPTO50LB 23KG BAGGAGE","count":1,"description":["Up to 50 lb/23 kg"],"kind":"qpxexpress#bagDescriptor","subcode":"0C3"},{"commercialName":"GOLF EQUIP UP TO 15KG 140CM","count":1,"description":["Small","Up to 33 lb/15 kg"],"kind":"qpxexpress#bagDescriptor","subcode":"S28"},{"commercialName":"GOLF EQUIP UP TO 32KG  2M","count":1,"description":["Medium","Up to 70 lb/32 kg"],"kind":"qpxexpress#bagDescriptor","subcode":"S29"},{"commercialName":"GOLF EQUIP UP TO 32KG OVER 2M","count":1,"description":["Large","Up to 70 lb/32 kg"],"kind":"qpxexpress#bagDescriptor","subcode":"S30"},{"commercialName":"SKI EQUIP UP TO 15KG 140CM","count":1,"description":["Small","Up to 33 lb/15 kg"],"kind":"qpxexpress#bagDescriptor","subcode":"S31"},{"commercialName":"SKI EQUIP UP TO 32KG 2M","count":1,"description":["Medium","Up to 70 lb/32 kg"],"kind":"qpxexpress#bagDescriptor","subcode":"S32"},{"commercialName":"SKI EQUIP UP TO 32KG OVER 2M","count":1,"description":["Large","Up to 70 lb/32 kg"],"kind":"qpxexpress#bagDescriptor","subcode":"S33"},{"commercialName":"WATER SKI EQUIP UPTO15KG 140CM","count":1,"description":["Small","Up to 33 lb/15 kg"],"kind":"qpxexpress#bagDescriptor","subcode":"S07"},{"commercialName":"WATER SKI EQUIP UP TO 32KG 2M","count":1,"description":["Medium","Up to 70 lb/32 kg"],"kind":"qpxexpress#bagDescriptor","subcode":"S08"},{"commercialName":"WATER SKI EQ UPTO 32KG OVER 2M","count":1,"description":["Large","Up to 70 lb/32 kg"],"kind":"qpxexpress#bagDescriptor","subcode":"S09"},{"commercialName":"SNOWBOARD UP TO 15KG 140CM","count":1,"description":["Small","Up to 33 lb/15 kg"],"kind":"qpxexpress#bagDescriptor","subcode":"S34"},{"commercialName":"SNOWBOARD UP TO 32KG  2M","count":1,"description":["Medium","Up to 70 lb/32 kg"],"kind":"qpxexpress#bagDescriptor","subcode":"S35"},{"commercialName":"SNOWBOARD UP TO 32KG OVER 2M","count":1,"description":["Large","Up to 70 lb/32 kg"],"kind":"qpxexpress#bagDescriptor","subcode":"S36"}],"kind":"qpxexpress#freeBaggageAllowance","pieces":1}],"kind":"qpxexpress#segmentPricing","segmentId":"G2aVxbWydHzJAd2u"}],"tax":[{"chargeType":"CARRIER_SURCHARGE","code":"YQ","id":"YQ_F","kind":"qpxexpress#taxInfo","salePrice":"EUR6.00"},{"chargeType":"CARRIER_SURCHARGE","code":"YR","id":"YR_F","kind":"qpxexpress#taxInfo","salePrice":"EUR76.00"},{"chargeType":"GOVERNMENT","code":"RA","country":"DE","id":"RA_002","kind":"qpxexpress#taxInfo","salePrice":"EUR16.66"},{"chargeType":"GOVERNMENT","code":"DE","country":"DE","id":"DE_001","kind":"qpxexpress#taxInfo","salePrice":"EUR4.05"},{"chargeType":"GOVERNMENT","code":"RD","country":"DE","id":"RD_002","kind":"qpxexpress#taxInfo","salePrice":"EUR9.93"},{"chargeType":"GOVERNMENT","code":"OY","country":"DE","id":"OY_001","kind":"qpxexpress#taxInfo","salePrice":"EUR7.50"}]}],"saleTotal":"EUR325.14","slice":[{"duration":485,"kind":"qpxexpress#sliceInfo","segment":[{"bookingCode":"Q","bookingCodeCount":4,"cabin":"COACH","connectionDuration":270,"duration":75,"flight":{"carrier":"A3","number":"1563"},"id":"GDvhNwpi-8lR0Kg1","kind":"qpxexpress#segmentInfo","leg":[{"aircraft":"321","arrivalTime":"2015-05-29T10:15+02:00","departureTime":"2015-05-29T09:00+02:00","destination":"MUC","destinationTerminal":"2","duration":75,"id":"LYSRXvfhYt1fbq7Q","kind":"qpxexpress#legInfo","meal":"Meal","mileage":372,"operatingDisclosure":"OPERATED BY LUFTHANSA","origin":"HAM","originTerminal":"2"}],"marriedSegmentGroup":"0"},{"bookingCode":"Q","bookingCodeCount":4,"cabin":"COACH","duration":140,"flight":{"carrier":"A3","number":"1806"},"id":"G2aVxbWydHzJAd2u","kind":"qpxexpress#segmentInfo","leg":[{"aircraft":"321","arrivalTime":"2015-05-29T18:05+03:00","departureTime":"2015-05-29T14:45+02:00","destination":"ATH","duration":140,"id":"LIi8zTihDGegZHq1","kind":"qpxexpress#legInfo","meal":"Meal","mileage":942,"operatingDisclosure":"OPERATED BY LUFTHANSA","origin":"MUC","originTerminal":"2"}],"marriedSegmentGroup":"1"}]}]},{"id":"Rns2hzSE8zQMCRWPJ1iNLU00B","kind":"qpxexpress#tripOption","pricing":[{"baseFareTotal":"EUR205.00","fare":[{"basisCode":"Q2A3DE","carrier":"A3","destination":"ATH","id":"ATSC/CKZ4neLQNIlNvyPR69lqOXl5wIFWMg4RGcyFF9v3","kind":"qpxexpress#fareInfo","origin":"HAM"}],"fareCalculation":"HAM A3 X/MUC A3 ATH M 224.43Q2A3DE NUC 224.43 END ROE 0.913391 FARE EUR 205.00 XT 4.05DE 7.50OY 16.66RA 9.93RD 6.00YQ 76.00YR","kind":"qpxexpress#pricingInfo","latestTicketingTime":"2015-05-29T01:59-04:00","passengers":{"adultCount":1,"kind":"qpxexpress#passengerCounts"},"ptc":"ADT","refundable":true,"saleFareTotal":"EUR205.00","saleTaxTotal":"EUR120.14","saleTotal":"EUR325.14","segmentPricing":[{"fareId":"ATSC/CKZ4neLQNIlNvyPR69lqOXl5wIFWMg4RGcyFF9v3","freeBaggageOption":[{"bagDescriptor":[{"commercialName":"UPTO50LB 23KG BAGGAGE","count":1,"description":["Up to 50 lb/23 kg"],"kind":"qpxexpress#bagDescriptor","subcode":"0C3"},{"commercialName":"GOLF EQUIP UP TO 15KG 140CM","count":1,"description":["Small","Up to 33 lb/15 kg"],"kind":"qpxexpress#bagDescriptor","subcode":"S28"},{"commercialName":"GOLF EQUIP UP TO 32KG  2M","count":1,"description":["Medium","Up to 70 lb/32 kg"],"kind":"qpxexpress#bagDescriptor","subcode":"S29"},{"commercialName":"GOLF EQUIP UP TO 32KG OVER 2M","count":1,"description":["Large","Up to 70 lb/32 kg"],"kind":"qpxexpress#bagDescriptor","subcode":"S30"},{"commercialName":"SKI EQUIP UP TO 15KG 140CM","count":1,"description":["Small","Up to 33 lb/15 kg"],"kind":"qpxexpress#bagDescriptor","subcode":"S31"},{"commercialName":"SKI EQUIP UP TO 32KG 2M","count":1,"description":["Medium","Up to 70 lb/32 kg"],"kind":"qpxexpress#bagDescriptor","subcode":"S32"},{"commercialName":"SKI EQUIP UP TO 32KG OVER 2M","count":1,"description":["Large","Up to 70 lb/32 kg"],"kind":"qpxexpress#bagDescriptor","subcode":"S33"},{"commercialName":"WATER SKI EQUIP UPTO15KG 140CM","count":1,"description":["Small","Up to 33 lb/15 kg"],"kind":"qpxexpress#bagDescriptor","subcode":"S07"},{"commercialName":"WATER SKI EQUIP UP TO 32KG 2M","count":1,"description":["Medium","Up to 70 lb/32 kg"],"kind":"qpxexpress#bagDescriptor","subcode":"S08"},{"commercialName":"WATER SKI EQ UPTO 32KG OVER 2M","count":1,"description":["Large","Up to 70 lb/32 kg"],"kind":"qpxexpress#bagDescriptor","subcode":"S09"},{"commercialName":"SNOWBOARD UP TO 15KG 140CM","count":1,"description":["Small","Up to 33 lb/15 kg"],"kind":"qpxexpress#bagDescriptor","subcode":"S34"},{"commercialName":"SNOWBOARD UP TO 32KG  2M","count":1,"description":["Medium","Up to 70 lb/32 kg"],"kind":"qpxexpress#bagDescriptor","subcode":"S35"},{"commercialName":"SNOWBOARD UP TO 32KG OVER 2M","count":1,"description":["Large","Up to 70 lb/32 kg"],"kind":"qpxexpress#bagDescriptor","subcode":"S36"}],"kind":"qpxexpress#freeBaggageAllowance","pieces":1}],"kind":"qpxexpress#segmentPricing","segmentId":"GyCXm28nW94n7nMD"},{"fareId":"ATSC/CKZ4neLQNIlNvyPR69lqOXl5wIFWMg4RGcyFF9v3","freeBaggageOption":[{"bagDescriptor":[{"commercialName":"UPTO50LB 23KG BAGGAGE","count":1,"description":["Up to 50 lb/23 kg"],"kind":"qpxexpress#bagDescriptor","subcode":"0C3"},{"commercialName":"GOLF EQUIP UP TO 15KG 140CM","count":1,"description":["Small","Up to 33 lb/15 kg"],"kind":"qpxexpress#bagDescriptor","subcode":"S28"},{"commercialName":"GOLF EQUIP UP TO 32KG  2M","count":1,"description":["Medium","Up to 70 lb/32 kg"],"kind":"qpxexpress#bagDescriptor","subcode":"S29"},{"commercialName":"GOLF EQUIP UP TO 32KG OVER 2M","count":1,"description":["Large","Up to 70 lb/32 kg"],"kind":"qpxexpress#bagDescriptor","subcode":"S30"},{"commercialName":"SKI EQUIP UP TO 15KG 140CM","count":1,"description":["Small","Up to 33 lb/15 kg"],"kind":"qpxexpress#bagDescriptor","subcode":"S31"},{"commercialName":"SKI EQUIP UP TO 32KG 2M","count":1,"description":["Medium","Up to 70 lb/32 kg"],"kind":"qpxexpress#bagDescriptor","subcode":"S32"},{"commercialName":"SKI EQUIP UP TO 32KG OVER 2M","count":1,"description":["Large","Up to 70 lb/32 kg"],"kind":"qpxexpress#bagDescriptor","subcode":"S33"},{"commercialName":"WATER SKI EQUIP UPTO15KG 140CM","count":1,"description":["Small","Up to 33 lb/15 kg"],"kind":"qpxexpress#bagDescriptor","subcode":"S07"},{"commercialName":"WATER SKI EQUIP UP TO 32KG 2M","count":1,"description":["Medium","Up to 70 lb/32 kg"],"kind":"qpxexpress#bagDescriptor","subcode":"S08"},{"commercialName":"WATER SKI EQ UPTO 32KG OVER 2M","count":1,"description":["Large","Up to 70 lb/32 kg"],"kind":"qpxexpress#bagDescriptor","subcode":"S09"},{"commercialName":"SNOWBOARD UP TO 15KG 140CM","count":1,"description":["Small","Up to 33 lb/15 kg"],"kind":"qpxexpress#bagDescriptor","subcode":"S34"},{"commercialName":"SNOWBOARD UP TO 32KG  2M","count":1,"description":["Medium","Up to 70 lb/32 kg"],"kind":"qpxexpress#bagDescriptor","subcode":"S35"},{"commercialName":"SNOWBOARD UP TO 32KG OVER 2M","count":1,"description":["Large","Up to 70 lb/32 kg"],"kind":"qpxexpress#bagDescriptor","subcode":"S36"}],"kind":"qpxexpress#freeBaggageAllowance","pieces":1}],"kind":"qpxexpress#segmentPricing","segmentId":"GhRXPXTXYxFm4t8d"}],"tax":[{"chargeType":"CARRIER_SURCHARGE","code":"YQ","id":"YQ_F","kind":"qpxexpress#taxInfo","salePrice":"EUR6.00"},{"chargeType":"CARRIER_SURCHARGE","code":"YR","id":"YR_F","kind":"qpxexpress#taxInfo","salePrice":"EUR76.00"},{"chargeType":"GOVERNMENT","code":"RA","country":"DE","id":"RA_002","kind":"qpxexpress#taxInfo","salePrice":"EUR16.66"},{"chargeType":"GOVERNMENT","code":"DE","country":"DE","id":"DE_001","kind":"qpxexpress#taxInfo","salePrice":"EUR4.05"},{"chargeType":"GOVERNMENT","code":"RD","country":"DE","id":"RD_002","kind":"qpxexpress#taxInfo","salePrice":"EUR9.93"},{"chargeType":"GOVERNMENT","code":"OY","country":"DE","id":"OY_001","kind":"qpxexpress#taxInfo","salePrice":"EUR7.50"}]}],"saleTotal":"EUR325.14","slice":[{"duration":800,"kind":"qpxexpress#sliceInfo","segment":[{"bookingCode":"Q","bookingCodeCount":4,"cabin":"COACH","connectionDuration":585,"duration":75,"flight":{"carrier":"A3","number":"1575"},"id":"GhRXPXTXYxFm4t8d","kind":"qpxexpress#segmentInfo","leg":[{"aircraft":"321","arrivalTime":"2015-05-29T09:15+02:00","departureTime":"2015-05-29T08:00+02:00","destination":"MUC","destinationTerminal":"2","duration":75,"id":"LfVkqc5bO6rLMyVY","kind":"qpxexpress#legInfo","meal":"Meal","mileage":372,"operatingDisclosure":"OPERATED BY LUFTHANSA","origin":"HAM","originTerminal":"2"}],"marriedSegmentGroup":"0"},{"bookingCode":"Q","bookingCodeCount":4,"cabin":"COACH","duration":140,"flight":{"carrier":"A3","number":"1808"},"id":"GyCXm28nW94n7nMD","kind":"qpxexpress#segmentInfo","leg":[{"aircraft":"321","arrivalTime":"2015-05-29T22:20+03:00","departureTime":"2015-05-29T19:00+02:00","destination":"ATH","duration":140,"id":"LvNgsAYdHo2RXzLX","kind":"qpxexpress#legInfo","meal":"Meal","mileage":942,"operatingDisclosure":"OPERATED BY LUFTHANSA","origin":"MUC","originTerminal":"2"}],"marriedSegmentGroup":"1"}]}]},{"id":"Rns2hzSE8zQMCRWPJ1iNLU009","kind":"qpxexpress#tripOption","pricing":[{"baseFareTotal":"EUR205.00","fare":[{"basisCode":"Q2A3DE","carrier":"A3","destination":"ATH","id":"ATSC/CKZ4neLQNIlNvyPR69lqOXl5wIFWMg4RGcyFF9v3","kind":"qpxexpress#fareInfo","origin":"HAM"}],"fareCalculation":"HAM A3 X/MUC A3 ATH M 224.43Q2A3DE NUC 224.43 END ROE 0.913391 FARE EUR 205.00 XT 4.05DE 7.50OY 16.66RA 9.93RD 6.00YQ 76.00YR","kind":"qpxexpress#pricingInfo","latestTicketingTime":"2015-05-29T02:59-04:00","passengers":{"adultCount":1,"kind":"qpxexpress#passengerCounts"},"ptc":"ADT","refundable":true,"saleFareTotal":"EUR205.00","saleTaxTotal":"EUR120.14","saleTotal":"EUR325.14","segmentPricing":[{"fareId":"ATSC/CKZ4neLQNIlNvyPR69lqOXl5wIFWMg4RGcyFF9v3","freeBaggageOption":[{"bagDescriptor":[{"commercialName":"UPTO50LB 23KG BAGGAGE","count":1,"description":["Up to 50 lb/23 kg"],"kind":"qpxexpress#bagDescriptor","subcode":"0C3"},{"commercialName":"GOLF EQUIP UP TO 15KG 140CM","count":1,"description":["Small","Up to 33 lb/15 kg"],"kind":"qpxexpress#bagDescriptor","subcode":"S28"},{"commercialName":"GOLF EQUIP UP TO 32KG  2M","count":1,"description":["Medium","Up to 70 lb/32 kg"],"kind":"qpxexpress#bagDescriptor","subcode":"S29"},{"commercialName":"GOLF EQUIP UP TO 32KG OVER 2M","count":1,"description":["Large","Up to 70 lb/32 kg"],"kind":"qpxexpress#bagDescriptor","subcode":"S30"},{"commercialName":"SKI EQUIP UP TO 15KG 140CM","count":1,"description":["Small","Up to 33 lb/15 kg"],"kind":"qpxexpress#bagDescriptor","subcode":"S31"},{"commercialName":"SKI EQUIP UP TO 32KG 2M","count":1,"description":["Medium","Up to 70 lb/32 kg"],"kind":"qpxexpress#bagDescriptor","subcode":"S32"},{"commercialName":"SKI EQUIP UP TO 32KG OVER 2M","count":1,"description":["Large","Up to 70 lb/32 kg"],"kind":"qpxexpress#bagDescriptor","subcode":"S33"},{"commercialName":"WATER SKI EQUIP UPTO15KG 140CM","count":1,"description":["Small","Up to 33 lb/15 kg"],"kind":"qpxexpress#bagDescriptor","subcode":"S07"},{"commercialName":"WATER SKI EQUIP UP TO 32KG 2M","count":1,"description":["Medium","Up to 70 lb/32 kg"],"kind":"qpxexpress#bagDescriptor","subcode":"S08"},{"commercialName":"WATER SKI EQ UPTO 32KG OVER 2M","count":1,"description":["Large","Up to 70 lb/32 kg"],"kind":"qpxexpress#bagDescriptor","subcode":"S09"},{"commercialName":"SNOWBOARD UP TO 15KG 140CM","count":1,"description":["Small","Up to 33 lb/15 kg"],"kind":"qpxexpress#bagDescriptor","subcode":"S34"},{"commercialName":"SNOWBOARD UP TO 32KG  2M","count":1,"description":["Medium","Up to 70 lb/32 kg"],"kind":"qpxexpress#bagDescriptor","subcode":"S35"},{"commercialName":"SNOWBOARD UP TO 32KG OVER 2M","count":1,"description":["Large","Up to 70 lb/32 kg"],"kind":"qpxexpress#bagDescriptor","subcode":"S36"}],"kind":"qpxexpress#freeBaggageAllowance","pieces":1}],"kind":"qpxexpress#segmentPricing","segmentId":"GDvhNwpi-8lR0Kg1"},{"fareId":"ATSC/CKZ4neLQNIlNvyPR69lqOXl5wIFWMg4RGcyFF9v3","freeBaggageOption":[{"bagDescriptor":[{"commercialName":"UPTO50LB 23KG BAGGAGE","count":1,"description":["Up to 50 lb/23 kg"],"kind":"qpxexpress#bagDescriptor","subcode":"0C3"},{"commercialName":"GOLF EQUIP UP TO 15KG 140CM","count":1,"description":["Small","Up to 33 lb/15 kg"],"kind":"qpxexpress#bagDescriptor","subcode":"S28"},{"commercialName":"GOLF EQUIP UP TO 32KG  2M","count":1,"description":["Medium","Up to 70 lb/32 kg"],"kind":"qpxexpress#bagDescriptor","subcode":"S29"},{"commercialName":"GOLF EQUIP UP TO 32KG OVER 2M","count":1,"description":["Large","Up to 70 lb/32 kg"],"kind":"qpxexpress#bagDescriptor","subcode":"S30"},{"commercialName":"SKI EQUIP UP TO 15KG 140CM","count":1,"description":["Small","Up to 33 lb/15 kg"],"kind":"qpxexpress#bagDescriptor","subcode":"S31"},{"commercialName":"SKI EQUIP UP TO 32KG 2M","count":1,"description":["Medium","Up to 70 lb/32 kg"],"kind":"qpxexpress#bagDescriptor","subcode":"S32"},{"commercialName":"SKI EQUIP UP TO 32KG OVER 2M","count":1,"description":["Large","Up to 70 lb/32 kg"],"kind":"qpxexpress#bagDescriptor","subcode":"S33"},{"commercialName":"WATER SKI EQUIP UPTO15KG 140CM","count":1,"description":["Small","Up to 33 lb/15 kg"],"kind":"qpxexpress#bagDescriptor","subcode":"S07"},{"commercialName":"WATER SKI EQUIP UP TO 32KG 2M","count":1,"description":["Medium","Up to 70 lb/32 kg"],"kind":"qpxexpress#bagDescriptor","subcode":"S08"},{"commercialName":"WATER SKI EQ UPTO 32KG OVER 2M","count":1,"description":["Large","Up to 70 lb/32 kg"],"kind":"qpxexpress#bagDescriptor","subcode":"S09"},{"commercialName":"SNOWBOARD UP TO 15KG 140CM","count":1,"description":["Small","Up to 33 lb/15 kg"],"kind":"qpxexpress#bagDescriptor","subcode":"S34"},{"commercialName":"SNOWBOARD UP TO 32KG  2M","count":1,"description":["Medium","Up to 70 lb/32 kg"],"kind":"qpxexpress#bagDescriptor","subcode":"S35"},{"commercialName":"SNOWBOARD UP TO 32KG OVER 2M","count":1,"description":["Large","Up to 70 lb/32 kg"],"kind":"qpxexpress#bagDescriptor","subcode":"S36"}],"kind":"qpxexpress#freeBaggageAllowance","pieces":1}],"kind":"qpxexpress#segmentPricing","segmentId":"GyCXm28nW94n7nMD"}],"tax":[{"chargeType":"CARRIER_SURCHARGE","code":"YQ","id":"YQ_F","kind":"qpxexpress#taxInfo","salePrice":"EUR6.00"},{"chargeType":"CARRIER_SURCHARGE","code":"YR","id":"YR_F","kind":"qpxexpress#taxInfo","salePrice":"EUR76.00"},{"chargeType":"GOVERNMENT","code":"RA","country":"DE","id":"RA_002","kind":"qpxexpress#taxInfo","salePrice":"EUR16.66"},{"chargeType":"GOVERNMENT","code":"DE","country":"DE","id":"DE_001","kind":"qpxexpress#taxInfo","salePrice":"EUR4.05"},{"chargeType":"GOVERNMENT","code":"RD","country":"DE","id":"RD_002","kind":"qpxexpress#taxInfo","salePrice":"EUR9.93"},{"chargeType":"GOVERNMENT","code":"OY","country":"DE","id":"OY_001","kind":"qpxexpress#taxInfo","salePrice":"EUR7.50"}]}],"saleTotal":"EUR325.14","slice":[{"duration":740,"kind":"qpxexpress#sliceInfo","segment":[{"bookingCode":"Q","bookingCodeCount":4,"cabin":"COACH","connectionDuration":525,"duration":75,"flight":{"carrier":"A3","number":"1563"},"id":"GDvhNwpi-8lR0Kg1","kind":"qpxexpress#segmentInfo","leg":[{"aircraft":"321","arrivalTime":"2015-05-29T10:15+02:00","departureTime":"2015-05-29T09:00+02:00","destination":"MUC","destinationTerminal":"2","duration":75,"id":"LYSRXvfhYt1fbq7Q","kind":"qpxexpress#legInfo","meal":"Meal","mileage":372,"operatingDisclosure":"OPERATED BY LUFTHANSA","origin":"HAM","originTerminal":"2"}],"marriedSegmentGroup":"0"},{"bookingCode":"Q","bookingCodeCount":4,"cabin":"COACH","duration":140,"flight":{"carrier":"A3","number":"1808"},"id":"GyCXm28nW94n7nMD","kind":"qpxexpress#segmentInfo","leg":[{"aircraft":"321","arrivalTime":"2015-05-29T22:20+03:00","departureTime":"2015-05-29T19:00+02:00","destination":"ATH","duration":140,"id":"LvNgsAYdHo2RXzLX","kind":"qpxexpress#legInfo","meal":"Meal","mileage":942,"operatingDisclosure":"OPERATED BY LUFTHANSA","origin":"MUC","originTerminal":"2"}],"marriedSegmentGroup":"1"}]}]},{"id":"Rns2hzSE8zQMCRWPJ1iNLU002","kind":"qpxexpress#tripOption","pricing":[{"baseFareTotal":"EUR229.00","fare":[{"basisCode":"HRCLOWEU","carrier":"SN","destination":"ATH","id":"AxsHwURvr3d2Pg88YD7uDCpxNPbb1+bbxSi48dkzDFBM","kind":"qpxexpress#fareInfo","origin":"HAM"}],"fareCalculation":"HAM SN X/BRU SN ATH 250.71HRCLOWEU NUC 250.71 END ROE 0.913391 FARE EUR 229.00 XT 4.05DE 7.50OY 9.93RA 18.38BE 86.00YQ","kind":"qpxexpress#pricingInfo","latestTicketingTime":"2015-05-27T15:46-04:00","passengers":{"adultCount":1,"kind":"qpxexpress#passengerCounts"},"ptc":"ADT","refundable":true,"saleFareTotal":"EUR229.00","saleTaxTotal":"EUR125.86","saleTotal":"EUR354.86","segmentPricing":[{"fareId":"AxsHwURvr3d2Pg88YD7uDCpxNPbb1+bbxSi48dkzDFBM","freeBaggageOption":[{"bagDescriptor":[{"commercialName":"UPTO50LB 23KG AND62LI 158LCM","count":1,"description":["Up to 50 lb/23 kg","Up to 62 li/158 lcm"],"kind":"qpxexpress#bagDescriptor","subcode":"0GO"},{"commercialName":"SPORTING EQUIPMENT SMALL","count":1,"description":["Small"],"kind":"qpxexpress#bagDescriptor","subcode":"0EF"},{"commercialName":"SKI EQUIPMENT","count":1,"description":["Ski Equipment"],"kind":"qpxexpress#bagDescriptor","subcode":"0DD"}],"kind":"qpxexpress#freeBaggageAllowance","pieces":1}],"kind":"qpxexpress#segmentPricing","segmentId":"Gzt+56Zi5s8Po5e5"},{"fareId":"AxsHwURvr3d2Pg88YD7uDCpxNPbb1+bbxSi48dkzDFBM","freeBaggageOption":[{"bagDescriptor":[{"commercialName":"UPTO50LB 23KG AND62LI 158LCM","count":1,"description":["Up to 50 lb/23 kg","Up to 62 li/158 lcm"],"kind":"qpxexpress#bagDescriptor","subcode":"0GO"},{"commercialName":"SPORTING EQUIPMENT SMALL","count":1,"description":["Small"],"kind":"qpxexpress#bagDescriptor","subcode":"0EF"},{"commercialName":"SKI EQUIPMENT","count":1,"description":["Ski Equipment"],"kind":"qpxexpress#bagDescriptor","subcode":"0DD"}],"kind":"qpxexpress#freeBaggageAllowance","pieces":1}],"kind":"qpxexpress#segmentPricing","segmentId":"G6-o3-GNL-co3uUM"}],"tax":[{"chargeType":"CARRIER_SURCHARGE","code":"YQ","id":"YQ_I","kind":"qpxexpress#taxInfo","salePrice":"EUR86.00"},{"chargeType":"GOVERNMENT","code":"BE","country":"BE","id":"BE_001","kind":"qpxexpress#taxInfo","salePrice":"EUR18.38"},{"chargeType":"GOVERNMENT","code":"DE","country":"DE","id":"DE_001","kind":"qpxexpress#taxInfo","salePrice":"EUR4.05"},{"chargeType":"GOVERNMENT","code":"RA","country":"DE","id":"RA_002","kind":"qpxexpress#taxInfo","salePrice":"EUR9.93"},{"chargeType":"GOVERNMENT","code":"OY","country":"DE","id":"OY_001","kind":"qpxexpress#taxInfo","salePrice":"EUR7.50"}]}],"saleTotal":"EUR354.86","slice":[{"duration":300,"kind":"qpxexpress#sliceInfo","segment":[{"bookingCode":"H","bookingCodeCount":9,"cabin":"COACH","connectionDuration":45,"duration":70,"flight":{"carrier":"SN","number":"2630"},"id":"Gzt+56Zi5s8Po5e5","kind":"qpxexpress#segmentInfo","leg":[{"aircraft":"319","arrivalTime":"2015-05-29T08:40+02:00","departureTime":"2015-05-29T07:30+02:00","destination":"BRU","duration":70,"id":"LrRvO4nyYdmMf+QW","kind":"qpxexpress#legInfo","meal":"Breakfast","mileage":299,"origin":"HAM","originTerminal":"2"}],"marriedSegmentGroup":"0"},{"bookingCode":"H","bookingCodeCount":9,"cabin":"COACH","duration":185,"flight":{"carrier":"SN","number":"3245"},"id":"G6-o3-GNL-co3uUM","kind":"qpxexpress#segmentInfo","leg":[{"aircraft":"319","arrivalTime":"2015-05-29T13:30+03:00","departureTime":"2015-05-29T09:25+02:00","destination":"ATH","duration":185,"id":"L5vTTZt0uUB7nYXt","kind":"qpxexpress#legInfo","meal":"Breakfast","mileage":1305,"origin":"BRU"}],"marriedSegmentGroup":"1"}]}]},{"id":"Rns2hzSE8zQMCRWPJ1iNLU00A","kind":"qpxexpress#tripOption","pricing":[{"baseFareTotal":"EUR229.00","fare":[{"basisCode":"HRCLOWEU","carrier":"SN","destination":"ATH","id":"AxsHwURvr3d2Pg88YD7uDCpxNPbb1+bbxSi48dkzDFBM","kind":"qpxexpress#fareInfo","origin":"HAM"}],"fareCalculation":"HAM SN X/BRU SN ATH 250.71HRCLOWEU NUC 250.71 END ROE 0.913391 FARE EUR 229.00 XT 4.05DE 7.50OY 9.93RA 18.38BE 86.00YQ","kind":"qpxexpress#pricingInfo","latestTicketingTime":"2015-05-27T15:46-04:00","passengers":{"adultCount":1,"kind":"qpxexpress#passengerCounts"},"ptc":"ADT","refundable":true,"saleFareTotal":"EUR229.00","saleTaxTotal":"EUR125.86","saleTotal":"EUR354.86","segmentPricing":[{"fareId":"AxsHwURvr3d2Pg88YD7uDCpxNPbb1+bbxSi48dkzDFBM","freeBaggageOption":[{"bagDescriptor":[{"commercialName":"UPTO50LB 23KG AND62LI 158LCM","count":1,"description":["Up to 50 lb/23 kg","Up to 62 li/158 lcm"],"kind":"qpxexpress#bagDescriptor","subcode":"0GO"},{"commercialName":"SPORTING EQUIPMENT SMALL","count":1,"description":["Small"],"kind":"qpxexpress#bagDescriptor","subcode":"0EF"},{"commercialName":"SKI EQUIPMENT","count":1,"description":["Ski Equipment"],"kind":"qpxexpress#bagDescriptor","subcode":"0DD"}],"kind":"qpxexpress#freeBaggageAllowance","pieces":1}],"kind":"qpxexpress#segmentPricing","segmentId":"GAJ3NwFhL8WkH02k"},{"fareId":"AxsHwURvr3d2Pg88YD7uDCpxNPbb1+bbxSi48dkzDFBM","freeBaggageOption":[{"bagDescriptor":[{"commercialName":"UPTO50LB 23KG AND62LI 158LCM","count":1,"description":["Up to 50 lb/23 kg","Up to 62 li/158 lcm"],"kind":"qpxexpress#bagDescriptor","subcode":"0GO"},{"commercialName":"SPORTING EQUIPMENT SMALL","count":1,"description":["Small"],"kind":"qpxexpress#bagDescriptor","subcode":"0EF"},{"commercialName":"SKI EQUIPMENT","count":1,"description":["Ski Equipment"],"kind":"qpxexpress#bagDescriptor","subcode":"0DD"}],"kind":"qpxexpress#freeBaggageAllowance","pieces":1}],"kind":"qpxexpress#segmentPricing","segmentId":"GV29Z5zprnGiB74s"}],"tax":[{"chargeType":"CARRIER_SURCHARGE","code":"YQ","id":"YQ_I","kind":"qpxexpress#taxInfo","salePrice":"EUR86.00"},{"chargeType":"GOVERNMENT","code":"BE","country":"BE","id":"BE_001","kind":"qpxexpress#taxInfo","salePrice":"EUR18.38"},{"chargeType":"GOVERNMENT","code":"DE","country":"DE","id":"DE_001","kind":"qpxexpress#taxInfo","salePrice":"EUR4.05"},{"chargeType":"GOVERNMENT","code":"RA","country":"DE","id":"RA_002","kind":"qpxexpress#taxInfo","salePrice":"EUR9.93"},{"chargeType":"GOVERNMENT","code":"OY","country":"DE","id":"OY_001","kind":"qpxexpress#taxInfo","salePrice":"EUR7.50"}]}],"saleTotal":"EUR354.86","slice":[{"duration":720,"kind":"qpxexpress#sliceInfo","segment":[{"bookingCode":"H","bookingCodeCount":9,"cabin":"COACH","connectionDuration":460,"duration":70,"flight":{"carrier":"SN","number":"2624"},"id":"GV29Z5zprnGiB74s","kind":"qpxexpress#segmentInfo","leg":[{"aircraft":"AR1","arrivalTime":"2015-05-29T12:35+02:00","departureTime":"2015-05-29T11:25+02:00","destination":"BRU","duration":70,"id":"LjN6u+1doylz5NTe","kind":"qpxexpress#legInfo","meal":"Snack or Brunch","mileage":299,"origin":"HAM","originTerminal":"2"}],"marriedSegmentGroup":"0"},{"bookingCode":"H","bookingCodeCount":4,"cabin":"COACH","duration":190,"flight":{"carrier":"SN","number":"6523"},"id":"GAJ3NwFhL8WkH02k","kind":"qpxexpress#segmentInfo","leg":[{"aircraft":"320","arrivalTime":"2015-05-30T00:25+03:00","departureTime":"2015-05-29T20:15+02:00","destination":"ATH","duration":190,"id":"LBIe-jwydMAJui2v","kind":"qpxexpress#legInfo","mileage":1305,"operatingDisclosure":"OPERATED BY AEGEAN AIRLINES","origin":"BRU"}],"marriedSegmentGroup":"1"}]}]},{"id":"Rns2hzSE8zQMCRWPJ1iNLU003","kind":"qpxexpress#tripOption","pricing":[{"baseFareTotal":"EUR272.00","fare":[{"basisCode":"H2A3DE","carrier":"A3","destination":"ATH","id":"AmstyvYEF4xZ8n2DashWXtpmMph6U2SD/BUf1/6qfeNeJ","kind":"qpxexpress#fareInfo","origin":"HAM"}],"fareCalculation":"HAM A3 X/FRA A3 ATH Q41.60 M 256.18H2A3DE NUC 297.78 END ROE 0.913391 FARE EUR 272.00 XT 4.05DE 7.50OY 21.19RA 9.93RD 6.00YQ 38.00YR","kind":"qpxexpress#pricingInfo","latestTicketingTime":"2015-05-29T09:59-04:00","passengers":{"adultCount":1,"kind":"qpxexpress#passengerCounts"},"ptc":"ADT","refundable":true,"saleFareTotal":"EUR272.00","saleTaxTotal":"EUR86.67","saleTotal":"EUR358.67","segmentPricing":[{"fareId":"AmstyvYEF4xZ8n2DashWXtpmMph6U2SD/BUf1/6qfeNeJ","freeBaggageOption":[{"bagDescriptor":[{"commercialName":"UPTO50LB 23KG BAGGAGE","count":1,"description":["Up to 50 lb/23 kg"],"kind":"qpxexpress#bagDescriptor","subcode":"0C3"},{"commercialName":"GOLF EQUIP UP TO 15KG 140CM","count":1,"description":["Small","Up to 33 lb/15 kg"],"kind":"qpxexpress#bagDescriptor","subcode":"S28"},{"commercialName":"GOLF EQUIP UP TO 32KG  2M","count":1,"description":["Medium","Up to 70 lb/32 kg"],"kind":"qpxexpress#bagDescriptor","subcode":"S29"},{"commercialName":"GOLF EQUIP UP TO 32KG OVER 2M","count":1,"description":["Large","Up to 70 lb/32 kg"],"kind":"qpxexpress#bagDescriptor","subcode":"S30"},{"commercialName":"SKI EQUIP UP TO 15KG 140CM","count":1,"description":["Small","Up to 33 lb/15 kg"],"kind":"qpxexpress#bagDescriptor","subcode":"S31"},{"commercialName":"SKI EQUIP UP TO 32KG 2M","count":1,"description":["Medium","Up to 70 lb/32 kg"],"kind":"qpxexpress#bagDescriptor","subcode":"S32"},{"commercialName":"SKI EQUIP UP TO 32KG OVER 2M","count":1,"description":["Large","Up to 70 lb/32 kg"],"kind":"qpxexpress#bagDescriptor","subcode":"S33"},{"commercialName":"WATER SKI EQUIP UPTO15KG 140CM","count":1,"description":["Small","Up to 33 lb/15 kg"],"kind":"qpxexpress#bagDescriptor","subcode":"S07"},{"commercialName":"WATER SKI EQUIP UP TO 32KG 2M","count":1,"description":["Medium","Up to 70 lb/32 kg"],"kind":"qpxexpress#bagDescriptor","subcode":"S08"},{"commercialName":"WATER SKI EQ UPTO 32KG OVER 2M","count":1,"description":["Large","Up to 70 lb/32 kg"],"kind":"qpxexpress#bagDescriptor","subcode":"S09"},{"commercialName":"SNOWBOARD UP TO 15KG 140CM","count":1,"description":["Small","Up to 33 lb/15 kg"],"kind":"qpxexpress#bagDescriptor","subcode":"S34"},{"commercialName":"SNOWBOARD UP TO 32KG  2M","count":1,"description":["Medium","Up to 70 lb/32 kg"],"kind":"qpxexpress#bagDescriptor","subcode":"S35"},{"commercialName":"SNOWBOARD UP TO 32KG OVER 2M","count":1,"description":["Large","Up to 70 lb/32 kg"],"kind":"qpxexpress#bagDescriptor","subcode":"S36"}],"kind":"qpxexpress#freeBaggageAllowance","pieces":1}],"kind":"qpxexpress#segmentPricing","segmentId":"GuC4aumm9M8i5Yzk"},{"fareId":"AmstyvYEF4xZ8n2DashWXtpmMph6U2SD/BUf1/6qfeNeJ","freeBaggageOption":[{"bagDescriptor":[{"commercialName":"UPTO50LB 23KG BAGGAGE","count":1,"description":["Up to 50 lb/23 kg"],"kind":"qpxexpress#bagDescriptor","subcode":"0C3"},{"commercialName":"GOLF EQUIP UP TO 15KG 140CM","count":1,"description":["Small","Up to 33 lb/15 kg"],"kind":"qpxexpress#bagDescriptor","subcode":"S28"},{"commercialName":"GOLF EQUIP UP TO 32KG  2M","count":1,"description":["Medium","Up to 70 lb/32 kg"],"kind":"qpxexpress#bagDescriptor","subcode":"S29"},{"commercialName":"GOLF EQUIP UP TO 32KG OVER 2M","count":1,"description":["Large","Up to 70 lb/32 kg"],"kind":"qpxexpress#bagDescriptor","subcode":"S30"},{"commercialName":"SKI EQUIP UP TO 15KG 140CM","count":1,"description":["Small","Up to 33 lb/15 kg"],"kind":"qpxexpress#bagDescriptor","subcode":"S31"},{"commercialName":"SKI EQUIP UP TO 32KG 2M","count":1,"description":["Medium","Up to 70 lb/32 kg"],"kind":"qpxexpress#bagDescriptor","subcode":"S32"},{"commercialName":"SKI EQUIP UP TO 32KG OVER 2M","count":1,"description":["Large","Up to 70 lb/32 kg"],"kind":"qpxexpress#bagDescriptor","subcode":"S33"},{"commercialName":"WATER SKI EQUIP UPTO15KG 140CM","count":1,"description":["Small","Up to 33 lb/15 kg"],"kind":"qpxexpress#bagDescriptor","subcode":"S07"},{"commercialName":"WATER SKI EQUIP UP TO 32KG 2M","count":1,"description":["Medium","Up to 70 lb/32 kg"],"kind":"qpxexpress#bagDescriptor","subcode":"S08"},{"commercialName":"WATER SKI EQ UPTO 32KG OVER 2M","count":1,"description":["Large","Up to 70 lb/32 kg"],"kind":"qpxexpress#bagDescriptor","subcode":"S09"},{"commercialName":"SNOWBOARD UP TO 15KG 140CM","count":1,"description":["Small","Up to 33 lb/15 kg"],"kind":"qpxexpress#bagDescriptor","subcode":"S34"},{"commercialName":"SNOWBOARD UP TO 32KG  2M","count":1,"description":["Medium","Up to 70 lb/32 kg"],"kind":"qpxexpress#bagDescriptor","subcode":"S35"},{"commercialName":"SNOWBOARD UP TO 32KG OVER 2M","count":1,"description":["Large","Up to 70 lb/32 kg"],"kind":"qpxexpress#bagDescriptor","subcode":"S36"}],"kind":"qpxexpress#freeBaggageAllowance","pieces":1}],"kind":"qpxexpress#segmentPricing","segmentId":"GvouwLABkUrYis8G"}],"tax":[{"chargeType":"GOVERNMENT","code":"RA","country":"DE","id":"RA_002","kind":"qpxexpress#taxInfo","salePrice":"EUR21.19"},{"chargeType":"CARRIER_SURCHARGE","code":"YQ","id":"YQ_F","kind":"qpxexpress#taxInfo","salePrice":"EUR6.00"},{"chargeType":"GOVERNMENT","code":"DE","country":"DE","id":"DE_001","kind":"qpxexpress#taxInfo","salePrice":"EUR4.05"},{"chargeType":"GOVERNMENT","code":"RD","country":"DE","id":"RD_002","kind":"qpxexpress#taxInfo","salePrice":"EUR9.93"},{"chargeType":"GOVERNMENT","code":"OY","country":"DE","id":"OY_001","kind":"qpxexpress#taxInfo","salePrice":"EUR7.50"},{"chargeType":"CARRIER_SURCHARGE","code":"YR","id":"YR_F","kind":"qpxexpress#taxInfo","salePrice":"EUR38.00"}]}],"saleTotal":"EUR358.67","slice":[{"duration":295,"kind":"qpxexpress#sliceInfo","segment":[{"bookingCode":"H","bookingCodeCount":4,"cabin":"COACH","connectionDuration":50,"duration":70,"flight":{"carrier":"A3","number":"1561"},"id":"GuC4aumm9M8i5Yzk","kind":"qpxexpress#segmentInfo","leg":[{"aircraft":"319","arrivalTime":"2015-05-29T17:10+02:00","departureTime":"2015-05-29T16:00+02:00","destination":"FRA","destinationTerminal":"1","duration":70,"id":"LMyJf3fDXJRBiA9e","kind":"qpxexpress#legInfo","meal":"Meal","mileage":255,"operatingDisclosure":"OPERATED BY LUFTHANSA","origin":"HAM","originTerminal":"2"}],"marriedSegmentGroup":"0"},{"bookingCode":"H","bookingCodeCount":9,"cabin":"COACH","duration":175,"flight":{"carrier":"A3","number":"833"},"id":"GvouwLABkUrYis8G","kind":"qpxexpress#segmentInfo","leg":[{"aircraft":"321","arrivalTime":"2015-05-29T21:55+03:00","departureTime":"2015-05-29T18:00+02:00","destination":"ATH","duration":175,"id":"LeCl+nIvki8Bb1H-","kind":"qpxexpress#legInfo","meal":"Hot Meal","mileage":1127,"origin":"FRA","originTerminal":"1"}],"marriedSegmentGroup":"1"}]}]},{"id":"Rns2hzSE8zQMCRWPJ1iNLU006","kind":"qpxexpress#tripOption","pricing":[{"baseFareTotal":"EUR234.00","fare":[{"basisCode":"H2A3DE","carrier":"A3","destination":"ATH","id":"AmstyvYEF4xZ8n2DashWXtpmMph6U2SD/BUf1/6qfeNeJ","kind":"qpxexpress#fareInfo","origin":"HAM"}],"fareCalculation":"HAM A3 X/FRA A3 ATH M 256.18H2A3DE NUC 256.18 END ROE 0.913391 FARE EUR 234.00 XT 4.05DE 7.50OY 21.19RA 9.93RD 6.00YQ 76.00YR","kind":"qpxexpress#pricingInfo","latestTicketingTime":"2015-05-29T09:59-04:00","passengers":{"adultCount":1,"kind":"qpxexpress#passengerCounts"},"ptc":"ADT","refundable":true,"saleFareTotal":"EUR234.00","saleTaxTotal":"EUR124.67","saleTotal":"EUR358.67","segmentPricing":[{"fareId":"AmstyvYEF4xZ8n2DashWXtpmMph6U2SD/BUf1/6qfeNeJ","freeBaggageOption":[{"bagDescriptor":[{"commercialName":"UPTO50LB 23KG BAGGAGE","count":1,"description":["Up to 50 lb/23 kg"],"kind":"qpxexpress#bagDescriptor","subcode":"0C3"},{"commercialName":"GOLF EQUIP UP TO 15KG 140CM","count":1,"description":["Small","Up to 33 lb/15 kg"],"kind":"qpxexpress#bagDescriptor","subcode":"S28"},{"commercialName":"GOLF EQUIP UP TO 32KG  2M","count":1,"description":["Medium","Up to 70 lb/32 kg"],"kind":"qpxexpress#bagDescriptor","subcode":"S29"},{"commercialName":"GOLF EQUIP UP TO 32KG OVER 2M","count":1,"description":["Large","Up to 70 lb/32 kg"],"kind":"qpxexpress#bagDescriptor","subcode":"S30"},{"commercialName":"SKI EQUIP UP TO 15KG 140CM","count":1,"description":["Small","Up to 33 lb/15 kg"],"kind":"qpxexpress#bagDescriptor","subcode":"S31"},{"commercialName":"SKI EQUIP UP TO 32KG 2M","count":1,"description":["Medium","Up to 70 lb/32 kg"],"kind":"qpxexpress#bagDescriptor","subcode":"S32"},{"commercialName":"SKI EQUIP UP TO 32KG OVER 2M","count":1,"description":["Large","Up to 70 lb/32 kg"],"kind":"qpxexpress#bagDescriptor","subcode":"S33"},{"commercialName":"WATER SKI EQUIP UPTO15KG 140CM","count":1,"description":["Small","Up to 33 lb/15 kg"],"kind":"qpxexpress#bagDescriptor","subcode":"S07"},{"commercialName":"WATER SKI EQUIP UP TO 32KG 2M","count":1,"description":["Medium","Up to 70 lb/32 kg"],"kind":"qpxexpress#bagDescriptor","subcode":"S08"},{"commercialName":"WATER SKI EQ UPTO 32KG OVER 2M","count":1,"description":["Large","Up to 70 lb/32 kg"],"kind":"qpxexpress#bagDescriptor","subcode":"S09"},{"commercialName":"SNOWBOARD UP TO 15KG 140CM","count":1,"description":["Small","Up to 33 lb/15 kg"],"kind":"qpxexpress#bagDescriptor","subcode":"S34"},{"commercialName":"SNOWBOARD UP TO 32KG  2M","count":1,"description":["Medium","Up to 70 lb/32 kg"],"kind":"qpxexpress#bagDescriptor","subcode":"S35"},{"commercialName":"SNOWBOARD UP TO 32KG OVER 2M","count":1,"description":["Large","Up to 70 lb/32 kg"],"kind":"qpxexpress#bagDescriptor","subcode":"S36"}],"kind":"qpxexpress#freeBaggageAllowance","pieces":1}],"kind":"qpxexpress#segmentPricing","segmentId":"GuC4aumm9M8i5Yzk"},{"fareId":"AmstyvYEF4xZ8n2DashWXtpmMph6U2SD/BUf1/6qfeNeJ","freeBaggageOption":[{"bagDescriptor":[{"commercialName":"UPTO50LB 23KG BAGGAGE","count":1,"description":["Up to 50 lb/23 kg"],"kind":"qpxexpress#bagDescriptor","subcode":"0C3"},{"commercialName":"GOLF EQUIP UP TO 15KG 140CM","count":1,"description":["Small","Up to 33 lb/15 kg"],"kind":"qpxexpress#bagDescriptor","subcode":"S28"},{"commercialName":"GOLF EQUIP UP TO 32KG  2M","count":1,"description":["Medium","Up to 70 lb/32 kg"],"kind":"qpxexpress#bagDescriptor","subcode":"S29"},{"commercialName":"GOLF EQUIP UP TO 32KG OVER 2M","count":1,"description":["Large","Up to 70 lb/32 kg"],"kind":"qpxexpress#bagDescriptor","subcode":"S30"},{"commercialName":"SKI EQUIP UP TO 15KG 140CM","count":1,"description":["Small","Up to 33 lb/15 kg"],"kind":"qpxexpress#bagDescriptor","subcode":"S31"},{"commercialName":"SKI EQUIP UP TO 32KG 2M","count":1,"description":["Medium","Up to 70 lb/32 kg"],"kind":"qpxexpress#bagDescriptor","subcode":"S32"},{"commercialName":"SKI EQUIP UP TO 32KG OVER 2M","count":1,"description":["Large","Up to 70 lb/32 kg"],"kind":"qpxexpress#bagDescriptor","subcode":"S33"},{"commercialName":"WATER SKI EQUIP UPTO15KG 140CM","count":1,"description":["Small","Up to 33 lb/15 kg"],"kind":"qpxexpress#bagDescriptor","subcode":"S07"},{"commercialName":"WATER SKI EQUIP UP TO 32KG 2M","count":1,"description":["Medium","Up to 70 lb/32 kg"],"kind":"qpxexpress#bagDescriptor","subcode":"S08"},{"commercialName":"WATER SKI EQ UPTO 32KG OVER 2M","count":1,"description":["Large","Up to 70 lb/32 kg"],"kind":"qpxexpress#bagDescriptor","subcode":"S09"},{"commercialName":"SNOWBOARD UP TO 15KG 140CM","count":1,"description":["Small","Up to 33 lb/15 kg"],"kind":"qpxexpress#bagDescriptor","subcode":"S34"},{"commercialName":"SNOWBOARD UP TO 32KG  2M","count":1,"description":["Medium","Up to 70 lb/32 kg"],"kind":"qpxexpress#bagDescriptor","subcode":"S35"},{"commercialName":"SNOWBOARD UP TO 32KG OVER 2M","count":1,"description":["Large","Up to 70 lb/32 kg"],"kind":"qpxexpress#bagDescriptor","subcode":"S36"}],"kind":"qpxexpress#freeBaggageAllowance","pieces":1}],"kind":"qpxexpress#segmentPricing","segmentId":"G4U2CoSFO6V9NWuV"}],"tax":[{"chargeType":"GOVERNMENT","code":"RA","country":"DE","id":"RA_002","kind":"qpxexpress#taxInfo","salePrice":"EUR21.19"},{"chargeType":"CARRIER_SURCHARGE","code":"YQ","id":"YQ_F","kind":"qpxexpress#taxInfo","salePrice":"EUR6.00"},{"chargeType":"CARRIER_SURCHARGE","code":"YR","id":"YR_F","kind":"qpxexpress#taxInfo","salePrice":"EUR76.00"},{"chargeType":"GOVERNMENT","code":"DE","country":"DE","id":"DE_001","kind":"qpxexpress#taxInfo","salePrice":"EUR4.05"},{"chargeType":"GOVERNMENT","code":"RD","country":"DE","id":"RD_002","kind":"qpxexpress#taxInfo","salePrice":"EUR9.93"},{"chargeType":"GOVERNMENT","code":"OY","country":"DE","id":"OY_001","kind":"qpxexpress#taxInfo","salePrice":"EUR7.50"}]}],"saleTotal":"EUR358.67","slice":[{"duration":445,"kind":"qpxexpress#sliceInfo","segment":[{"bookingCode":"H","bookingCodeCount":4,"cabin":"COACH","connectionDuration":210,"duration":70,"flight":{"carrier":"A3","number":"1561"},"id":"GuC4aumm9M8i5Yzk","kind":"qpxexpress#segmentInfo","leg":[{"aircraft":"319","arrivalTime":"2015-05-29T17:10+02:00","departureTime":"2015-05-29T16:00+02:00","destination":"FRA","destinationTerminal":"1","duration":70,"id":"LMyJf3fDXJRBiA9e","kind":"qpxexpress#legInfo","meal":"Meal","mileage":255,"operatingDisclosure":"OPERATED BY LUFTHANSA","origin":"HAM","originTerminal":"2"}],"marriedSegmentGroup":"0"},{"bookingCode":"H","bookingCodeCount":4,"cabin":"COACH","duration":165,"flight":{"carrier":"A3","number":"1834"},"id":"G4U2CoSFO6V9NWuV","kind":"qpxexpress#segmentInfo","leg":[{"aircraft":"321","arrivalTime":"2015-05-30T00:25+03:00","departureTime":"2015-05-29T20:40+02:00","destination":"ATH","duration":165,"id":"LpF3kgToHF9RfMWY","kind":"qpxexpress#legInfo","meal":"Meal","mileage":1127,"operatingDisclosure":"OPERATED BY LUFTHANSA","origin":"FRA","originTerminal":"1"}],"marriedSegmentGroup":"1"}]}]},{"id":"Rns2hzSE8zQMCRWPJ1iNLU004","kind":"qpxexpress#tripOption","pricing":[{"baseFareTotal":"EUR240.00","fare":[{"basisCode":"MDEOWM","carrier":"SK","destination":"ATH","id":"AfC/d3DjHgSRr3D9ItVuJRz7J1zXCclIJQwliMlieQXE","kind":"qpxexpress#fareInfo","origin":"HAM"}],"fareCalculation":"HAM SK X/CPH SK ATH 262.75MDEOWM NUC 262.75 END ROE 0.913391 FARE EUR 240.00 XT 4.05DE 7.50OY 9.93RA 15.02ZO 86.00YQ","kind":"qpxexpress#pricingInfo","latestTicketingTime":"2015-05-26T23:59-04:00","passengers":{"adultCount":1,"kind":"qpxexpress#passengerCounts"},"ptc":"ADT","saleFareTotal":"EUR240.00","saleTaxTotal":"EUR122.50","saleTotal":"EUR362.50","segmentPricing":[{"fareId":"AfC/d3DjHgSRr3D9ItVuJRz7J1zXCclIJQwliMlieQXE","freeBaggageOption":[{"bagDescriptor":[{"commercialName":"UPTO50LB 23KG BAGGAGE","count":1,"description":["Up to 50 lb/23 kg"],"kind":"qpxexpress#bagDescriptor","subcode":"0C3"},{"count":1,"kind":"qpxexpress#bagDescriptor","subcode":"0HS"},{"commercialName":"GOLF EQUIPMENT UP TO 50LB 23KG","count":1,"description":["Golf Equipment","Up to 50 lb/23 kg"],"kind":"qpxexpress#bagDescriptor","subcode":"0HQ"},{"count":1,"kind":"qpxexpress#bagDescriptor","subcode":"0HY"},{"count":1,"kind":"qpxexpress#bagDescriptor","subcode":"0HU"},{"count":1,"kind":"qpxexpress#bagDescriptor","subcode":"0OF"},{"count":1,"kind":"qpxexpress#bagDescriptor","subcode":"0O0"},{"count":1,"kind":"qpxexpress#bagDescriptor","subcode":"0KN"},{"count":1,"kind":"qpxexpress#bagDescriptor","subcode":"0KS"}],"kind":"qpxexpress#freeBaggageAllowance","pieces":1}],"kind":"qpxexpress#segmentPricing","segmentId":"Ga9D2qwyNP4oWIdG"},{"fareId":"AfC/d3DjHgSRr3D9ItVuJRz7J1zXCclIJQwliMlieQXE","freeBaggageOption":[{"bagDescriptor":[{"commercialName":"UPTO50LB 23KG BAGGAGE","count":1,"description":["Up to 50 lb/23 kg"],"kind":"qpxexpress#bagDescriptor","subcode":"0C3"},{"count":1,"kind":"qpxexpress#bagDescriptor","subcode":"0HS"},{"commercialName":"GOLF EQUIPMENT UP TO 50LB 23KG","count":1,"description":["Golf Equipment","Up to 50 lb/23 kg"],"kind":"qpxexpress#bagDescriptor","subcode":"0HQ"},{"count":1,"kind":"qpxexpress#bagDescriptor","subcode":"0HY"},{"count":1,"kind":"qpxexpress#bagDescriptor","subcode":"0HU"},{"count":1,"kind":"qpxexpress#bagDescriptor","subcode":"0OF"},{"count":1,"kind":"qpxexpress#bagDescriptor","subcode":"0O0"},{"count":1,"kind":"qpxexpress#bagDescriptor","subcode":"0KN"},{"count":1,"kind":"qpxexpress#bagDescriptor","subcode":"0KS"}],"kind":"qpxexpress#freeBaggageAllowance","pieces":1}],"kind":"qpxexpress#segmentPricing","segmentId":"GUq6wziBX4DqLPsU"}],"tax":[{"chargeType":"CARRIER_SURCHARGE","code":"YQ","id":"YQ_F","kind":"qpxexpress#taxInfo","salePrice":"EUR86.00"},{"chargeType":"GOVERNMENT","code":"ZO","country":"DK","id":"ZO_003","kind":"qpxexpress#taxInfo","salePrice":"EUR15.02"},{"chargeType":"GOVERNMENT","code":"DE","country":"DE","id":"DE_001","kind":"qpxexpress#taxInfo","salePrice":"EUR4.05"},{"chargeType":"GOVERNMENT","code":"RA","country":"DE","id":"RA_002","kind":"qpxexpress#taxInfo","salePrice":"EUR9.93"},{"chargeType":"GOVERNMENT","code":"OY","country":"DE","id":"OY_001","kind":"qpxexpress#taxInfo","salePrice":"EUR7.50"}]}],"saleTotal":"EUR362.50","slice":[{"duration":315,"kind":"qpxexpress#sliceInfo","segment":[{"bookingCode":"M","bookingCodeCount":9,"cabin":"COACH","connectionDuration":75,"duration":50,"flight":{"carrier":"SK","number":"648"},"id":"GUq6wziBX4DqLPsU","kind":"qpxexpress#segmentInfo","leg":[{"aircraft":"CR9","arrivalTime":"2015-05-29T07:25+02:00","departureTime":"2015-05-29T06:35+02:00","destination":"CPH","destinationTerminal":"3","duration":50,"id":"LrP1wP20DqyNzUGW","kind":"qpxexpress#legInfo","meal":"No Meal","mileage":173,"operatingDisclosure":"OPERATED BY CIMBER A/S","origin":"HAM","originTerminal":"2"}],"marriedSegmentGroup":"0"},{"bookingCode":"M","bookingCodeCount":9,"cabin":"COACH","duration":190,"flight":{"carrier":"SK","number":"777"},"id":"Ga9D2qwyNP4oWIdG","kind":"qpxexpress#segmentInfo","leg":[{"aircraft":"321","arrivalTime":"2015-05-29T12:50+03:00","departureTime":"2015-05-29T08:40+02:00","destination":"ATH","duration":190,"id":"L+1RpT68xBX+ae9o","kind":"qpxexpress#legInfo","meal":"Food and Beverages for Purchase","mileage":1329,"origin":"CPH","originTerminal":"3"}],"marriedSegmentGroup":"1"}]}]}]}}